{
	"m_AtlasName": "",
	"m_AtlasRD": {
		"m_AlphaTexture": { "m_Collection": "cab-3c0b6d0158b163c9df24e66fb67aff1a", "m_PathID": 0 },
		"m_AtlasRectOffset": {
			"m_X": 0,
			"m_Y": 0
		},
		"m_Bindpose": [
			
		],
		"m_DownscaleMultiplier": 0,
		"m_IndexBuffer": "",
		"m_SecondaryTextures": [
			
		],
		"m_SettingsRaw": 0,
		"m_SubMeshes": [
			
		],
		"m_Texture": { "m_Collection": "cab-3c0b6d0158b163c9df24e66fb67aff1a", "m_PathID": 0 },
		"m_TextureRect": {
			"m_Height": 0,
			"m_Width": 0,
			"m_X": 0,
			"m_Y": 0
		},
		"m_TextureRectOffset": {
			"m_X": 0,
			"m_Y": 0
		},
		"m_UvTransform": {
			"m_W": 0,
			"m_X": 0,
			"m_Y": 0,
			"m_Z": 0
		},
		"m_VertexData": {
			"m_Channels": [
				
			],
			"m_Data": "",
			"m_VertexCount": 0
		}
	},
	"m_AtlasTags": [
		
	],
	"m_Bones": [
		
	],
	"m_Border": {
		"m_W": 0,
		"m_X": 0,
		"m_Y": 0,
		"m_Z": 0
	},
	"m_CorrespondingSourceObject": { "m_Collection": "cab-3c0b6d0158b163c9df24e66fb67aff1a", "m_PathID": 0 },
	"m_Extrude": 1,
	"m_HideFlags": 0,
	"m_IsPolygon": false,
	"m_Name": "2022_foodcube_skin_SuspPink_killGun_imposter0019",
	"m_Offset": {
		"m_X": 292.96188,
		"m_Y": 68.50001
	},
	"m_PackingTag": "",
	"m_PhysicsShape": [
		[
			{
				"m_X": -2.55,
				"m_Y": -1.24
			},
			{
				"m_X": -2.47,
				"m_Y": -1.23
			},
			{
				"m_X": -2.3899999,
				"m_Y": -1.13
			},
			{
				"m_X": -2.37,
				"m_Y": -1
			},
			{
				"m_X": -2.27,
				"m_Y": -0.90999997
			},
			{
				"m_X": -2.27,
				"m_Y": -0.84999996
			},
			{
				"m_X": -2.34,
				"m_Y": -0.65999997
			},
			{
				"m_X": -2.26,
				"m_Y": -0.59999996
			},
			{
				"m_X": -2.26,
				"m_Y": -0.19999999
			},
			{
				"m_X": -2.29,
				"m_Y": -0.17
			},
			{
				"m_X": -2.3999999,
				"m_Y": -0.17
			},
			{
				"m_X": -2.6599998,
				"m_Y": -0.25
			},
			{
				"m_X": -3.1899998,
				"m_Y": -0.17999999
			},
			{
				"m_X": -3.29,
				"m_Y": -0.099999994
			},
			{
				"m_X": -3.36,
				"m_Y": -0.06
			},
			{
				"m_X": -3.58,
				"m_Y": -0.06
			},
			{
				"m_X": -3.59,
				"m_Y": -0.22999999
			},
			{
				"m_X": -3.59,
				"m_Y": -0.28
			},
			{
				"m_X": -3.5,
				"m_Y": -0.35
			},
			{
				"m_X": -3.55,
				"m_Y": -0.48
			},
			{
				"m_X": -3.59,
				"m_Y": -0.61
			},
			{
				"m_X": -3.57,
				"m_Y": -0.72999996
			},
			{
				"m_X": -3.59,
				"m_Y": -0.85999995
			},
			{
				"m_X": -3.59,
				"m_Y": -0.97999996
			},
			{
				"m_X": -3.48,
				"m_Y": -1.25
			},
			{
				"m_X": -3.35,
				"m_Y": -1.3199999
			},
			{
				"m_X": -3.04,
				"m_Y": -1.3199999
			},
			{
				"m_X": -2.9199998,
				"m_Y": -1.26
			},
			{
				"m_X": -2.9099998,
				"m_Y": -1.2099999
			},
			{
				"m_X": -2.76,
				"m_Y": -1.25
			}
		],
		[
			{
				"m_X": -3.1299999,
				"m_Y": -1.05
			},
			{
				"m_X": -3.1599998,
				"m_Y": -1.05
			},
			{
				"m_X": -3.07,
				"m_Y": -1.05
			},
			{
				"m_X": -3.11,
				"m_Y": -1.09
			},
			{
				"m_X": -3.1,
				"m_Y": -1.09
			}
		],
		[
			{
				"m_X": -2.57,
				"m_Y": -1.02
			},
			{
				"m_X": -2.55,
				"m_Y": -1.01
			},
			{
				"m_X": -2.57,
				"m_Y": -1.03
			},
			{
				"m_X": -2.56,
				"m_Y": -1.03
			}
		]
	],
	"m_Pivot": {
		"m_X": 2.6875255,
		"m_Y": 1.0400175
	},
	"m_PixelsToUnits": 100,
	"m_PrefabAsset": { "m_Collection": "cab-3c0b6d0158b163c9df24e66fb67aff1a", "m_PathID": 0 },
	"m_PrefabInstance": { "m_Collection": "cab-3c0b6d0158b163c9df24e66fb67aff1a", "m_PathID": 0 },
	"m_RD": {
		"m_AlphaTexture": { "m_Collection": "cab-3c0b6d0158b163c9df24e66fb67aff1a", "m_PathID": 0 },
		"m_AtlasRectOffset": {
			"m_X": -1,
			"m_Y": -1
		},
		"m_Bindpose": [
			
		],
		"m_DownscaleMultiplier": 1,
		"m_IndexBuffer": "AwAEAAUAAAACAAMAAAADAAUAAAABAAIAAAAFAAYA",
		"m_SecondaryTextures": [
			
		],
		"m_SettingsRaw": 64,
		"m_SubMeshes": [
			{
				"m_BaseVertex": 0,
				"m_FirstByte": 0,
				"m_FirstVertex": 0,
				"m_IndexCount": 15,
				"m_LocalAABB": {
					"m_Center": {
						"m_X": 0,
						"m_Y": 0,
						"m_Z": 0
					},
					"m_Extent": {
						"m_X": 0,
						"m_Y": 0,
						"m_Z": 0
					}
				},
				"m_Topology": 0,
				"m_VertexCount": 7
			}
		],
		"m_Texture": { "m_Collection": "cab-3c0b6d0158b163c9df24e66fb67aff1a", "m_PathID": 7582248090424966086 },
		"m_TextureRect": {
			"m_Height": 126.847755,
			"m_Width": 133.92387,
			"m_X": 1126.0762,
			"m_Y": 810.0761
		},
		"m_TextureRectOffset": {
			"m_X": 0,
			"m_Y": 0
		},
		"m_UvTransform": {
			"m_W": 942,
			"m_X": 100,
			"m_Y": 1486,
			"m_Z": 100
		},
		"m_VertexData": {
			"m_Channels": [
				{
					"m_Dimension": 3,
					"m_Format": 0,
					"m_Offset": 0,
					"m_Stream": 0
				},
				{
					"m_Dimension": 0,
					"m_Format": 0,
					"m_Offset": 0,
					"m_Stream": 0
				},
				{
					"m_Dimension": 0,
					"m_Format": 0,
					"m_Offset": 0,
					"m_Stream": 0
				},
				{
					"m_Dimension": 0,
					"m_Format": 0,
					"m_Offset": 0,
					"m_Stream": 0
				},
				{
					"m_Dimension": 2,
					"m_Format": 0,
					"m_Offset": 0,
					"m_Stream": 1
				},
				{
					"m_Dimension": 0,
					"m_Format": 0,
					"m_Offset": 0,
					"m_Stream": 0
				},
				{
					"m_Dimension": 0,
					"m_Format": 0,
					"m_Offset": 0,
					"m_Stream": 0
				},
				{
					"m_Dimension": 0,
					"m_Format": 0,
					"m_Offset": 0,
					"m_Stream": 0
				},
				{
					"m_Dimension": 0,
					"m_Format": 0,
					"m_Offset": 0,
					"m_Stream": 0
				},
				{
					"m_Dimension": 0,
					"m_Format": 0,
					"m_Offset": 0,
					"m_Stream": 0
				},
				{
					"m_Dimension": 0,
					"m_Format": 0,
					"m_Offset": 0,
					"m_Stream": 0
				},
				{
					"m_Dimension": 0,
					"m_Format": 0,
					"m_Offset": 0,
					"m_Stream": 0
				},
				{
					"m_Dimension": 0,
					"m_Format": 0,
					"m_Offset": 0,
					"m_Stream": 0
				},
				{
					"m_Dimension": 0,
					"m_Format": 0,
					"m_Offset": 0,
					"m_Stream": 0
				}
			],
			"m_Data": "mZk5wOtROL4AAAAA16MQwJmZGb4AAAAA16MQwHsUbr8AAAAAzcwcwKRwnb8AAAAAHoVbwIXrsb8AAAAAZmZmwNejcL8AAAAAj8JlwArXI7wAAAAAAAAAAAAAAAAAAAAAAAAAAAAAAAAAAAAAAAAAAAAAAAAAAAAAAAAAAAAAAAAAAAAAAAAAAAAAAAAAAAAAAAAAAAAAAAA=",
			"m_VertexCount": 7
		}
	},
	"m_Rect": {
		"m_Height": 126.847755,
		"m_Width": 133.92387,
		"m_X": 1126.0762,
		"m_Y": 810.0761
	},
	"m_RenderDataKey": {
		"Key": {
			"m_Data_0_": 3476685273,
			"m_Data_1_": 1233227714,
			"m_Data_2_": 952076183,
			"m_Data_3_": 30508782
		},
		"Value": 6290474087435465020
	},
	"m_SpriteAtlas": { "m_Collection": "cab-3c0b6d0158b163c9df24e66fb67aff1a", "m_PathID": 0 },
	"m_SpriteID": ""
}