{
	"m_AtlasName": "",
	"m_AtlasRD": {
		"m_AlphaTexture": { "m_Collection": "cab-3c0b6d0158b163c9df24e66fb67aff1a", "m_PathID": 0 },
		"m_AtlasRectOffset": {
			"m_X": 0,
			"m_Y": 0
		},
		"m_Bindpose": [
			
		],
		"m_DownscaleMultiplier": 0,
		"m_IndexBuffer": "",
		"m_SecondaryTextures": [
			
		],
		"m_SettingsRaw": 0,
		"m_SubMeshes": [
			
		],
		"m_Texture": { "m_Collection": "cab-3c0b6d0158b163c9df24e66fb67aff1a", "m_PathID": 0 },
		"m_TextureRect": {
			"m_Height": 0,
			"m_Width": 0,
			"m_X": 0,
			"m_Y": 0
		},
		"m_TextureRectOffset": {
			"m_X": 0,
			"m_Y": 0
		},
		"m_UvTransform": {
			"m_W": 0,
			"m_X": 0,
			"m_Y": 0,
			"m_Z": 0
		},
		"m_VertexData": {
			"m_Channels": [
				
			],
			"m_Data": "",
			"m_VertexCount": 0
		}
	},
	"m_AtlasTags": [
		
	],
	"m_Bones": [
		
	],
	"m_Border": {
		"m_W": 0,
		"m_X": 0,
		"m_Y": 0,
		"m_Z": 0
	},
	"m_CorrespondingSourceObject": { "m_Collection": "cab-3c0b6d0158b163c9df24e66fb67aff1a", "m_PathID": 0 },
	"m_Extrude": 1,
	"m_HideFlags": 0,
	"m_IsPolygon": false,
	"m_Name": "2022_hololive_Star_Skin_shirakamiFubuki_SpawnMirror0014",
	"m_Offset": {
		"m_X": -65.02467,
		"m_Y": 27.03806
	},
	"m_PackingTag": "",
	"m_PhysicsShape": [
		[
			{
				"m_X": 0.91499996,
				"m_Y": -0.84999996
			},
			{
				"m_X": 0.865,
				"m_Y": -0.87
			},
			{
				"m_X": 0.835,
				"m_Y": -0.90999997
			},
			{
				"m_X": 0.835,
				"m_Y": -0.91999996
			},
			{
				"m_X": 1.035,
				"m_Y": -0.91999996
			},
			{
				"m_X": 1.035,
				"m_Y": -0.9
			},
			{
				"m_X": 1.005,
				"m_Y": -0.85999995
			},
			{
				"m_X": 0.97499996,
				"m_Y": -0.84999996
			}
		],
		[
			{
				"m_X": 1.535,
				"m_Y": -0.22999999
			},
			{
				"m_X": 1.535,
				"m_Y": -0.16
			},
			{
				"m_X": 1.385,
				"m_Y": -0.06
			},
			{
				"m_X": 1.4449999,
				"m_Y": 0
			},
			{
				"m_X": 1.485,
				"m_Y": 0.12
			},
			{
				"m_X": 1.425,
				"m_Y": 0.25
			},
			{
				"m_X": 1.3149999,
				"m_Y": 0.34
			},
			{
				"m_X": 1.185,
				"m_Y": 0.34
			},
			{
				"m_X": 0.945,
				"m_Y": 0.19999999
			},
			{
				"m_X": 0.48499998,
				"m_Y": 0.19
			},
			{
				"m_X": 0.225,
				"m_Y": 0.32999998
			},
			{
				"m_X": 0.024999999,
				"m_Y": 0.25
			},
			{
				"m_X": -0.015,
				"m_Y": 0.01
			},
			{
				"m_X": -0.205,
				"m_Y": -0.14999999
			},
			{
				"m_X": -0.225,
				"m_Y": -0.24
			},
			{
				"m_X": -0.225,
				"m_Y": -0.5
			},
			{
				"m_X": -0.145,
				"m_Y": -0.61
			},
			{
				"m_X": 0.035,
				"m_Y": -0.69
			},
			{
				"m_X": 0.225,
				"m_Y": -0.69
			},
			{
				"m_X": 0.315,
				"m_Y": -0.77
			},
			{
				"m_X": 0.435,
				"m_Y": -0.82
			},
			{
				"m_X": 0.655,
				"m_Y": -0.82
			},
			{
				"m_X": 1.005,
				"m_Y": -0.68
			},
			{
				"m_X": 1.235,
				"m_Y": -0.48999998
			},
			{
				"m_X": 1.495,
				"m_Y": -0.29
			}
		],
		[
			{
				"m_X": 0.295,
				"m_Y": -0.11
			},
			{
				"m_X": 0.325,
				"m_Y": -0.12
			},
			{
				"m_X": 0.325,
				"m_Y": -0.14999999
			},
			{
				"m_X": 0.33499998,
				"m_Y": -0.14999999
			},
			{
				"m_X": 0.33499998,
				"m_Y": -0.14
			}
		]
	],
	"m_Pivot": {
		"m_X": 0.14831972,
		"m_Y": 0.70810694
	},
	"m_PixelsToUnits": 100,
	"m_PrefabAsset": { "m_Collection": "cab-3c0b6d0158b163c9df24e66fb67aff1a", "m_PathID": 0 },
	"m_PrefabInstance": { "m_Collection": "cab-3c0b6d0158b163c9df24e66fb67aff1a", "m_PathID": 0 },
	"m_RD": {
		"m_AlphaTexture": { "m_Collection": "cab-3c0b6d0158b163c9df24e66fb67aff1a", "m_PathID": 0 },
		"m_AtlasRectOffset": {
			"m_X": -1,
			"m_Y": -1
		},
		"m_Bindpose": [
			
		],
		"m_DownscaleMultiplier": 1,
		"m_IndexBuffer": "AwAGAAcAAwAFAAYAAAABAAcAAwAEAAUAAgADAAcAAQACAAcAAAAHAAgA",
		"m_SecondaryTextures": [
			
		],
		"m_SettingsRaw": 64,
		"m_SubMeshes": [
			{
				"m_BaseVertex": 0,
				"m_FirstByte": 0,
				"m_FirstVertex": 0,
				"m_IndexCount": 21,
				"m_LocalAABB": {
					"m_Center": {
						"m_X": 0,
						"m_Y": 0,
						"m_Z": 0
					},
					"m_Extent": {
						"m_X": 0,
						"m_Y": 0,
						"m_Z": 0
					}
				},
				"m_Topology": 0,
				"m_VertexCount": 9
			}
		],
		"m_Texture": { "m_Collection": "cab-3c0b6d0158b163c9df24e66fb67aff1a", "m_PathID": -3346273480782782025 },
		"m_TextureRect": {
			"m_Height": 129.92387,
			"m_Width": 184.89713,
			"m_X": 603.0761,
			"m_Y": 1270
		},
		"m_TextureRectOffset": {
			"m_X": 0,
			"m_Y": 0
		},
		"m_UvTransform": {
			"m_W": 1362,
			"m_X": 100,
			"m_Y": 630.5,
			"m_Z": 100
		},
		"m_VertexData": {
			"m_Channels": [
				{
					"m_Dimension": 3,
					"m_Format": 0,
					"m_Offset": 0,
					"m_Stream": 0
				},
				{
					"m_Dimension": 0,
					"m_Format": 0,
					"m_Offset": 0,
					"m_Stream": 0
				},
				{
					"m_Dimension": 0,
					"m_Format": 0,
					"m_Offset": 0,
					"m_Stream": 0
				},
				{
					"m_Dimension": 0,
					"m_Format": 0,
					"m_Offset": 0,
					"m_Stream": 0
				},
				{
					"m_Dimension": 2,
					"m_Format": 0,
					"m_Offset": 0,
					"m_Stream": 1
				},
				{
					"m_Dimension": 0,
					"m_Format": 0,
					"m_Offset": 0,
					"m_Stream": 0
				},
				{
					"m_Dimension": 0,
					"m_Format": 0,
					"m_Offset": 0,
					"m_Stream": 0
				},
				{
					"m_Dimension": 0,
					"m_Format": 0,
					"m_Offset": 0,
					"m_Stream": 0
				},
				{
					"m_Dimension": 0,
					"m_Format": 0,
					"m_Offset": 0,
					"m_Stream": 0
				},
				{
					"m_Dimension": 0,
					"m_Format": 0,
					"m_Offset": 0,
					"m_Stream": 0
				},
				{
					"m_Dimension": 0,
					"m_Format": 0,
					"m_Offset": 0,
					"m_Stream": 0
				},
				{
					"m_Dimension": 0,
					"m_Format": 0,
					"m_Offset": 0,
					"m_Stream": 0
				},
				{
					"m_Dimension": 0,
					"m_Format": 0,
					"m_Offset": 0,
					"m_Stream": 0
				},
				{
					"m_Dimension": 0,
					"m_Format": 0,
					"m_Offset": 0,
					"m_Stream": 0
				}
			],
			"m_Data": "exS+P5mZmT4AAAAApHDNPwAAgL4AAAAA61GIP4/CNb8AAAAACtcDPx6Fa78AAAAAFK6HvgrXI78AAAAAzcyMvlyPQr4AAAAAuB6FPTMzsz4AAAAAmZl5P+F6lD4AAAAA16OgP4Xr0T4AAAAAAAAAAAAAAAAAAAAAAAAAAAAAAAAAAAAAAAAAAAAAAAAAAAAAAAAAAAAAAAAAAAAAAAAAAAAAAAAAAAAAAAAAAAAAAAAAAAAAAAAAAA==",
			"m_VertexCount": 9
		}
	},
	"m_Rect": {
		"m_Height": 129.92387,
		"m_Width": 184.89713,
		"m_X": 603.0761,
		"m_Y": 1270
	},
	"m_RenderDataKey": {
		"Key": {
			"m_Data_0_": 52003952,
			"m_Data_1_": 1084105871,
			"m_Data_2_": 3262669448,
			"m_Data_3_": 719406792
		},
		"Value": 4714085746116649141
	},
	"m_SpriteAtlas": { "m_Collection": "cab-3c0b6d0158b163c9df24e66fb67aff1a", "m_PathID": 0 },
	"m_SpriteID": ""
}