{
	"m_AtlasName": "",
	"m_AtlasRD": {
		"m_AlphaTexture": { "m_Collection": "cab-3c0b6d0158b163c9df24e66fb67aff1a", "m_PathID": 0 },
		"m_AtlasRectOffset": {
			"m_X": 0,
			"m_Y": 0
		},
		"m_Bindpose": [
			
		],
		"m_DownscaleMultiplier": 0,
		"m_IndexBuffer": "",
		"m_SecondaryTextures": [
			
		],
		"m_SettingsRaw": 0,
		"m_SubMeshes": [
			
		],
		"m_Texture": { "m_Collection": "cab-3c0b6d0158b163c9df24e66fb67aff1a", "m_PathID": 0 },
		"m_TextureRect": {
			"m_Height": 0,
			"m_Width": 0,
			"m_X": 0,
			"m_Y": 0
		},
		"m_TextureRectOffset": {
			"m_X": 0,
			"m_Y": 0
		},
		"m_UvTransform": {
			"m_W": 0,
			"m_X": 0,
			"m_Y": 0,
			"m_Z": 0
		},
		"m_VertexData": {
			"m_Channels": [
				
			],
			"m_Data": "",
			"m_VertexCount": 0
		}
	},
	"m_AtlasTags": [
		
	],
	"m_Bones": [
		
	],
	"m_Border": {
		"m_W": 0,
		"m_X": 0,
		"m_Y": 0,
		"m_Z": 0
	},
	"m_CorrespondingSourceObject": { "m_Collection": "cab-3c0b6d0158b163c9df24e66fb67aff1a", "m_PathID": 0 },
	"m_Extrude": 1,
	"m_HideFlags": 0,
	"m_IsPolygon": false,
	"m_Name": "2022_hololive_Star_Skin_hoshouMarine_Kill_stab_Victim0038",
	"m_Offset": {
		"m_X": 35.02145,
		"m_Y": 70.96188
	},
	"m_PackingTag": "",
	"m_PhysicsShape": [
		[
			{
				"m_X": -0.11,
				"m_Y": -1.2049999
			},
			{
				"m_X": -0.02,
				"m_Y": -1.105
			},
			{
				"m_X": 0.17,
				"m_Y": -1.015
			},
			{
				"m_X": 0.25,
				"m_Y": -0.91499996
			},
			{
				"m_X": 0.31,
				"m_Y": -0.645
			},
			{
				"m_X": 0.41,
				"m_Y": -0.555
			},
			{
				"m_X": 0.48,
				"m_Y": -0.45499998
			},
			{
				"m_X": 0.48,
				"m_Y": -0.385
			},
			{
				"m_X": 0.44,
				"m_Y": -0.225
			},
			{
				"m_X": 0.38,
				"m_Y": -0.015
			},
			{
				"m_X": 0.31,
				"m_Y": 0.005
			},
			{
				"m_X": 0.22,
				"m_Y": 0.005
			},
			{
				"m_X": 0.14999999,
				"m_Y": -0.044999998
			},
			{
				"m_X": -0.11,
				"m_Y": -0.105
			},
			{
				"m_X": -0.24,
				"m_Y": -0.185
			},
			{
				"m_X": -0.38,
				"m_Y": -0.265
			},
			{
				"m_X": -0.42999998,
				"m_Y": -0.265
			},
			{
				"m_X": -0.66999996,
				"m_Y": -0.305
			},
			{
				"m_X": -0.78999996,
				"m_Y": -0.42499998
			},
			{
				"m_X": -0.95,
				"m_Y": -0.525
			},
			{
				"m_X": -0.9,
				"m_Y": -0.685
			},
			{
				"m_X": -1.04,
				"m_Y": -0.825
			},
			{
				"m_X": -1.17,
				"m_Y": -0.92499995
			},
			{
				"m_X": -1.17,
				"m_Y": -1.035
			},
			{
				"m_X": -1.12,
				"m_Y": -1.145
			},
			{
				"m_X": -1.15,
				"m_Y": -1.235
			},
			{
				"m_X": -1.14,
				"m_Y": -1.395
			},
			{
				"m_X": -1.02,
				"m_Y": -1.4649999
			},
			{
				"m_X": -0.78,
				"m_Y": -1.4649999
			},
			{
				"m_X": -0.69,
				"m_Y": -1.415
			},
			{
				"m_X": -0.37,
				"m_Y": -1.385
			},
			{
				"m_X": -0.22,
				"m_Y": -1.3149999
			}
		],
		[
			{
				"m_X": -1.17,
				"m_Y": -0.465
			},
			{
				"m_X": -1.18,
				"m_Y": -0.465
			},
			{
				"m_X": -1.18,
				"m_Y": -0.72499996
			},
			{
				"m_X": -1.14,
				"m_Y": -0.72499996
			},
			{
				"m_X": -1.06,
				"m_Y": -0.66499996
			},
			{
				"m_X": -1.06,
				"m_Y": -0.59499997
			}
		],
		[
			{
				"m_X": -0.9,
				"m_Y": 0.044999998
			},
			{
				"m_X": -0.9,
				"m_Y": -0.13499999
			},
			{
				"m_X": -0.78,
				"m_Y": -0.185
			},
			{
				"m_X": -0.26,
				"m_Y": -0.185
			},
			{
				"m_X": -0.19999999,
				"m_Y": -0.13499999
			},
			{
				"m_X": 0.049999997,
				"m_Y": -0.015
			},
			{
				"m_X": 0.049999997,
				"m_Y": 0.044999998
			}
		]
	],
	"m_Pivot": {
		"m_X": 0.71102715,
		"m_Y": 0.9701833
	},
	"m_PixelsToUnits": 100,
	"m_PrefabAsset": { "m_Collection": "cab-3c0b6d0158b163c9df24e66fb67aff1a", "m_PathID": 0 },
	"m_PrefabInstance": { "m_Collection": "cab-3c0b6d0158b163c9df24e66fb67aff1a", "m_PathID": 0 },
	"m_RD": {
		"m_AlphaTexture": { "m_Collection": "cab-3c0b6d0158b163c9df24e66fb67aff1a", "m_PathID": 0 },
		"m_AtlasRectOffset": {
			"m_X": -1,
			"m_Y": -1
		},
		"m_Bindpose": [
			
		],
		"m_DownscaleMultiplier": 1,
		"m_IndexBuffer": "AAAIAAkABgAHAAgABgAIAAEABQADAAQABQAGAAMAAgADAAYABgABAAIAAAABAAgA",
		"m_SecondaryTextures": [
			
		],
		"m_SettingsRaw": 64,
		"m_SubMeshes": [
			{
				"m_BaseVertex": 0,
				"m_FirstByte": 0,
				"m_FirstVertex": 0,
				"m_IndexCount": 24,
				"m_LocalAABB": {
					"m_Center": {
						"m_X": 0,
						"m_Y": 0,
						"m_Z": 0
					},
					"m_Extent": {
						"m_X": 0,
						"m_Y": 0,
						"m_Z": 0
					}
				},
				"m_Topology": 0,
				"m_VertexCount": 10
			}
		],
		"m_Texture": { "m_Collection": "cab-3c0b6d0158b163c9df24e66fb67aff1a", "m_PathID": 930718770049792423 },
		"m_TextureRect": {
			"m_Height": 150.92387,
			"m_Width": 165.95709,
			"m_X": 1832,
			"m_Y": 1396.0762
		},
		"m_TextureRectOffset": {
			"m_X": 0,
			"m_Y": 0
		},
		"m_UvTransform": {
			"m_W": 1542.5,
			"m_X": 100,
			"m_Y": 1950,
			"m_Z": 100
		},
		"m_VertexData": {
			"m_Channels": [
				{
					"m_Dimension": 3,
					"m_Format": 0,
					"m_Offset": 0,
					"m_Stream": 0
				},
				{
					"m_Dimension": 0,
					"m_Format": 0,
					"m_Offset": 0,
					"m_Stream": 0
				},
				{
					"m_Dimension": 0,
					"m_Format": 0,
					"m_Offset": 0,
					"m_Stream": 0
				},
				{
					"m_Dimension": 0,
					"m_Format": 0,
					"m_Offset": 0,
					"m_Stream": 0
				},
				{
					"m_Dimension": 2,
					"m_Format": 0,
					"m_Offset": 0,
					"m_Stream": 1
				},
				{
					"m_Dimension": 0,
					"m_Format": 0,
					"m_Offset": 0,
					"m_Stream": 0
				},
				{
					"m_Dimension": 0,
					"m_Format": 0,
					"m_Offset": 0,
					"m_Stream": 0
				},
				{
					"m_Dimension": 0,
					"m_Format": 0,
					"m_Offset": 0,
					"m_Stream": 0
				},
				{
					"m_Dimension": 0,
					"m_Format": 0,
					"m_Offset": 0,
					"m_Stream": 0
				},
				{
					"m_Dimension": 0,
					"m_Format": 0,
					"m_Offset": 0,
					"m_Stream": 0
				},
				{
					"m_Dimension": 0,
					"m_Format": 0,
					"m_Offset": 0,
					"m_Stream": 0
				},
				{
					"m_Dimension": 0,
					"m_Format": 0,
					"m_Offset": 0,
					"m_Stream": 0
				},
				{
					"m_Dimension": 0,
					"m_Format": 0,
					"m_Offset": 0,
					"m_Stream": 0
				},
				{
					"m_Dimension": 0,
					"m_Format": 0,
					"m_Offset": 0,
					"m_Stream": 0
				}
			],
			"m_Data": "AAAAP+F61L4AAAAAPQpXPpmZeb8AAAAAmZmZvq5Hsb8AAAAA61F4v3sUvr8AAAAAj8KVv65Hsb8AAAAAPQqXv3A9ar8AAAAAHoVrvylcL78AAAAAexRuv6Nw/b4AAAAAUrgev4Xrkb4AAAAAexSuPutROD0AAAAAAAAAAAAAAAAAAAAAAAAAAAAAAAAAAAAAAAAAAAAAAAAAAAAAAAAAAAAAAAAAAAAAAAAAAAAAAAAAAAAAAAAAAAAAAAAAAAAAAAAAAAAAAAAAAAAAAAAAAA==",
			"m_VertexCount": 10
		}
	},
	"m_Rect": {
		"m_Height": 150.92387,
		"m_Width": 165.95709,
		"m_X": 1832,
		"m_Y": 1396.0762
	},
	"m_RenderDataKey": {
		"Key": {
			"m_Data_0_": 37125011,
			"m_Data_1_": 1229310526,
			"m_Data_2_": 1446467513,
			"m_Data_3_": 97102811
		},
		"Value": -4591221540359305254
	},
	"m_SpriteAtlas": { "m_Collection": "cab-3c0b6d0158b163c9df24e66fb67aff1a", "m_PathID": 0 },
	"m_SpriteID": ""
}