{
	"m_AtlasName": "",
	"m_AtlasRD": {
		"m_AlphaTexture": { "m_Collection": "cab-e0567868cb12ecc3a595f02c77cb5b91", "m_PathID": 0 },
		"m_AtlasRectOffset": {
			"m_X": 0,
			"m_Y": 0
		},
		"m_Bindpose": [
			
		],
		"m_DownscaleMultiplier": 0,
		"m_IndexBuffer": "",
		"m_SecondaryTextures": [
			
		],
		"m_SettingsRaw": 0,
		"m_SubMeshes": [
			
		],
		"m_Texture": { "m_Collection": "cab-e0567868cb12ecc3a595f02c77cb5b91", "m_PathID": 0 },
		"m_TextureRect": {
			"m_Height": 0,
			"m_Width": 0,
			"m_X": 0,
			"m_Y": 0
		},
		"m_TextureRectOffset": {
			"m_X": 0,
			"m_Y": 0
		},
		"m_UvTransform": {
			"m_W": 0,
			"m_X": 0,
			"m_Y": 0,
			"m_Z": 0
		},
		"m_VertexData": {
			"m_Channels": [
				
			],
			"m_Data": "",
			"m_VertexCount": 0
		}
	},
	"m_AtlasTags": [
		
	],
	"m_Bones": [
		
	],
	"m_Border": {
		"m_W": 0,
		"m_X": 0,
		"m_Y": 0,
		"m_Z": 0
	},
	"m_CorrespondingSourceObject": { "m_Collection": "cab-e0567868cb12ecc3a595f02c77cb5b91", "m_PathID": 0 },
	"m_Extrude": 1,
	"m_HideFlags": 0,
	"m_IsPolygon": false,
	"m_Name": "2024_store_beans_hat_2025nye0004",
	"m_Offset": {
		"m_X": 5.500003,
		"m_Y": -71.5
	},
	"m_PackingTag": "",
	"m_PhysicsShape": [
		[
			{
				"m_X": 0.46999994,
				"m_Y": 0.42
			},
			{
				"m_X": 0.45999995,
				"m_Y": 0.48
			},
			{
				"m_X": 0.46999994,
				"m_Y": 0.51
			},
			{
				"m_X": 0.46999994,
				"m_Y": 0.64
			},
			{
				"m_X": 0.45999995,
				"m_Y": 0.68
			},
			{
				"m_X": 0.20999996,
				"m_Y": 0.72999996
			},
			{
				"m_X": 0.14999996,
				"m_Y": 0.66999996
			},
			{
				"m_X": 0.029999962,
				"m_Y": 0.82
			},
			{
				"m_X": 0.03999996,
				"m_Y": 0.95
			},
			{
				"m_X": 0.03999996,
				"m_Y": 1.06
			},
			{
				"m_X": 0.029999962,
				"m_Y": 1.1
			},
			{
				"m_X": -0.010000038,
				"m_Y": 1.1999999
			},
			{
				"m_X": -0.15000004,
				"m_Y": 1.36
			},
			{
				"m_X": -0.39000002,
				"m_Y": 1.36
			},
			{
				"m_X": -0.58000004,
				"m_Y": 1.17
			},
			{
				"m_X": -0.58000004,
				"m_Y": 0.90999997
			},
			{
				"m_X": -0.46000004,
				"m_Y": 0.78
			},
			{
				"m_X": -0.40000004,
				"m_Y": 0.76
			},
			{
				"m_X": -0.41000003,
				"m_Y": 0.61
			},
			{
				"m_X": -0.58000004,
				"m_Y": 0.48
			},
			{
				"m_X": -0.58000004,
				"m_Y": 0.34
			},
			{
				"m_X": -0.56,
				"m_Y": 0.19
			},
			{
				"m_X": -0.42000002,
				"m_Y": 0.07
			},
			{
				"m_X": -0.25000003,
				"m_Y": 0.07
			},
			{
				"m_X": 0.019999962,
				"m_Y": 0.13
			},
			{
				"m_X": 0.42999995,
				"m_Y": 0.17999999
			},
			{
				"m_X": 0.46999994,
				"m_Y": 0.21
			}
		]
	],
	"m_Pivot": {
		"m_X": 0.552381,
		"m_Y": -0.054263566
	},
	"m_PixelsToUnits": 100,
	"m_PrefabAsset": { "m_Collection": "cab-e0567868cb12ecc3a595f02c77cb5b91", "m_PathID": 0 },
	"m_PrefabInstance": { "m_Collection": "cab-e0567868cb12ecc3a595f02c77cb5b91", "m_PathID": 0 },
	"m_RD": {
		"m_AlphaTexture": { "m_Collection": "cab-e0567868cb12ecc3a595f02c77cb5b91", "m_PathID": 0 },
		"m_AtlasRectOffset": {
			"m_X": -1,
			"m_Y": -1
		},
		"m_Bindpose": [
			
		],
		"m_DownscaleMultiplier": 1,
		"m_IndexBuffer": "AAABAAIAAgABAAMA",
		"m_SecondaryTextures": [
			
		],
		"m_SettingsRaw": 0,
		"m_SubMeshes": [
			{
				"m_BaseVertex": 0,
				"m_FirstByte": 0,
				"m_FirstVertex": 0,
				"m_IndexCount": 6,
				"m_LocalAABB": {
					"m_Center": {
						"m_X": 0,
						"m_Y": 0,
						"m_Z": 0
					},
					"m_Extent": {
						"m_X": 0,
						"m_Y": 0,
						"m_Z": 0
					}
				},
				"m_Topology": 0,
				"m_VertexCount": 4
			}
		],
		"m_Texture": { "m_Collection": "cab-e0567868cb12ecc3a595f02c77cb5b91", "m_PathID": -632916485988753979 },
		"m_TextureRect": {
			"m_Height": 129,
			"m_Width": 105,
			"m_X": 1,
			"m_Y": 1
		},
		"m_TextureRectOffset": {
			"m_X": 0,
			"m_Y": 0
		},
		"m_UvTransform": {
			"m_W": -6,
			"m_X": 100,
			"m_Y": 59.000004,
			"m_Z": 100
		},
		"m_VertexData": {
			"m_Channels": [
				{
					"m_Dimension": 3,
					"m_Format": 0,
					"m_Offset": 0,
					"m_Stream": 0
				},
				{
					"m_Dimension": 0,
					"m_Format": 0,
					"m_Offset": 0,
					"m_Stream": 0
				},
				{
					"m_Dimension": 0,
					"m_Format": 0,
					"m_Offset": 0,
					"m_Stream": 0
				},
				{
					"m_Dimension": 0,
					"m_Format": 0,
					"m_Offset": 0,
					"m_Stream": 0
				},
				{
					"m_Dimension": 2,
					"m_Format": 0,
					"m_Offset": 0,
					"m_Stream": 1
				},
				{
					"m_Dimension": 0,
					"m_Format": 0,
					"m_Offset": 0,
					"m_Stream": 0
				},
				{
					"m_Dimension": 0,
					"m_Format": 0,
					"m_Offset": 0,
					"m_Stream": 0
				},
				{
					"m_Dimension": 0,
					"m_Format": 0,
					"m_Offset": 0,
					"m_Stream": 0
				},
				{
					"m_Dimension": 0,
					"m_Format": 0,
					"m_Offset": 0,
					"m_Stream": 0
				},
				{
					"m_Dimension": 0,
					"m_Format": 0,
					"m_Offset": 0,
					"m_Stream": 0
				},
				{
					"m_Dimension": 0,
					"m_Format": 0,
					"m_Offset": 0,
					"m_Stream": 0
				},
				{
					"m_Dimension": 0,
					"m_Format": 0,
					"m_Offset": 0,
					"m_Stream": 0
				},
				{
					"m_Dimension": 0,
					"m_Format": 0,
					"m_Offset": 0,
					"m_Stream": 0
				},
				{
					"m_Dimension": 0,
					"m_Format": 0,
					"m_Offset": 0,
					"m_Stream": 0
				}
			],
			"m_Data": "4noUv3sUrj8AAAAA1qPwPnsUrj8AAAAA4noUvylcjz0AAAAA1qPwPilcjz0AAAAAAAAAAAAAAAAAAAAAAAAAAAAAAAAAAAAAAAAAAAAAAAA=",
			"m_VertexCount": 4
		}
	},
	"m_Rect": {
		"m_Height": 129,
		"m_Width": 105,
		"m_X": 1,
		"m_Y": 1
	},
	"m_RenderDataKey": {
		"Key": {
			"m_Data_0_": 2446188170,
			"m_Data_1_": 1329450754,
			"m_Data_2_": 3485436847,
			"m_Data_3_": 3570467731
		},
		"Value": 2403217820915352327
	},
	"m_SpriteAtlas": { "m_Collection": "cab-e0567868cb12ecc3a595f02c77cb5b91", "m_PathID": 0 },
	"m_SpriteID": ""
}