{
	"m_AtlasName": "",
	"m_AtlasRD": {
		"m_AlphaTexture": { "m_Collection": "cab-3c0b6d0158b163c9df24e66fb67aff1a", "m_PathID": 0 },
		"m_AtlasRectOffset": {
			"m_X": 0,
			"m_Y": 0
		},
		"m_Bindpose": [
			
		],
		"m_DownscaleMultiplier": 0,
		"m_IndexBuffer": "",
		"m_SecondaryTextures": [
			
		],
		"m_SettingsRaw": 0,
		"m_SubMeshes": [
			
		],
		"m_Texture": { "m_Collection": "cab-3c0b6d0158b163c9df24e66fb67aff1a", "m_PathID": 0 },
		"m_TextureRect": {
			"m_Height": 0,
			"m_Width": 0,
			"m_X": 0,
			"m_Y": 0
		},
		"m_TextureRectOffset": {
			"m_X": 0,
			"m_Y": 0
		},
		"m_UvTransform": {
			"m_W": 0,
			"m_X": 0,
			"m_Y": 0,
			"m_Z": 0
		},
		"m_VertexData": {
			"m_Channels": [
				
			],
			"m_Data": "",
			"m_VertexCount": 0
		}
	},
	"m_AtlasTags": [
		
	],
	"m_Bones": [
		
	],
	"m_Border": {
		"m_W": 0,
		"m_X": 0,
		"m_Y": 0,
		"m_Z": 0
	},
	"m_CorrespondingSourceObject": { "m_Collection": "cab-3c0b6d0158b163c9df24e66fb67aff1a", "m_PathID": 0 },
	"m_Extrude": 1,
	"m_HideFlags": 0,
	"m_IsPolygon": false,
	"m_Name": "Bush_Spawn0023",
	"m_Offset": {
		"m_X": 74.984,
		"m_Y": 7.999998
	},
	"m_PackingTag": "",
	"m_PhysicsShape": [
		[
			{
				"m_X": -0.61,
				"m_Y": -0.19
			},
			{
				"m_X": -0.85999995,
				"m_Y": -0.32999998
			},
			{
				"m_X": -0.91999996,
				"m_Y": -0.48999998
			},
			{
				"m_X": -0.94,
				"m_Y": -0.53999996
			},
			{
				"m_X": 0.099999994,
				"m_Y": -0.53999996
			},
			{
				"m_X": 0.099999994,
				"m_Y": -0.29999998
			},
			{
				"m_X": 0.02,
				"m_Y": -0.19
			}
		],
		[
			{
				"m_X": -0.65999997,
				"m_Y": -0.13
			},
			{
				"m_X": -0.62,
				"m_Y": -0.12
			},
			{
				"m_X": -0.45999998,
				"m_Y": -0.14
			},
			{
				"m_X": -0.44,
				"m_Y": -0.13
			},
			{
				"m_X": -0.29999998,
				"m_Y": -0.089999996
			},
			{
				"m_X": -0.19,
				"m_Y": 0
			},
			{
				"m_X": 0.03,
				"m_Y": -0.089999996
			},
			{
				"m_X": 0.07,
				"m_Y": -0.08
			},
			{
				"m_X": 0.07,
				"m_Y": 0.07
			},
			{
				"m_X": -0.14,
				"m_Y": 0.32
			},
			{
				"m_X": -0.48999998,
				"m_Y": 0.29999998
			},
			{
				"m_X": -0.59,
				"m_Y": 0.21
			},
			{
				"m_X": -0.72999996,
				"m_Y": 0.34
			},
			{
				"m_X": -1.05,
				"m_Y": 0.32
			},
			{
				"m_X": -1.13,
				"m_Y": 0.26999998
			},
			{
				"m_X": -1.29,
				"m_Y": 0.35999998
			},
			{
				"m_X": -1.38,
				"m_Y": 0.35999998
			},
			{
				"m_X": -1.41,
				"m_Y": 0.35
			},
			{
				"m_X": -1.5899999,
				"m_Y": 0.11
			},
			{
				"m_X": -1.5899999,
				"m_Y": -0.16
			},
			{
				"m_X": -1.5699999,
				"m_Y": -0.29
			},
			{
				"m_X": -1.52,
				"m_Y": -0.39999998
			},
			{
				"m_X": -1.42,
				"m_Y": -0.47
			},
			{
				"m_X": -1.3299999,
				"m_Y": -0.48999998
			},
			{
				"m_X": -1.16,
				"m_Y": -0.53
			},
			{
				"m_X": -1.05,
				"m_Y": -0.53
			},
			{
				"m_X": -1.05,
				"m_Y": -0.48999998
			},
			{
				"m_X": -1.13,
				"m_Y": -0.35999998
			},
			{
				"m_X": -0.85999995,
				"m_Y": -0.13
			}
		],
		[
			{
				"m_X": -0.04,
				"m_Y": 0.38
			},
			{
				"m_X": -0.03,
				"m_Y": 0.34
			},
			{
				"m_X": 0.099999994,
				"m_Y": 0.34
			},
			{
				"m_X": 0.099999994,
				"m_Y": 0.38
			}
		]
	],
	"m_Pivot": {
		"m_X": 0.9411653,
		"m_Y": 0.5869565
	},
	"m_PixelsToUnits": 100,
	"m_PrefabAsset": { "m_Collection": "cab-3c0b6d0158b163c9df24e66fb67aff1a", "m_PathID": 0 },
	"m_PrefabInstance": { "m_Collection": "cab-3c0b6d0158b163c9df24e66fb67aff1a", "m_PathID": 0 },
	"m_RD": {
		"m_AlphaTexture": { "m_Collection": "cab-3c0b6d0158b163c9df24e66fb67aff1a", "m_PathID": 0 },
		"m_AtlasRectOffset": {
			"m_X": -1,
			"m_Y": -1
		},
		"m_Bindpose": [
			
		],
		"m_DownscaleMultiplier": 1,
		"m_IndexBuffer": "BAACAAMABAAFAAIAAgAFAAYAAAABAAIAAAACAAYA",
		"m_SecondaryTextures": [
			
		],
		"m_SettingsRaw": 64,
		"m_SubMeshes": [
			{
				"m_BaseVertex": 0,
				"m_FirstByte": 0,
				"m_FirstVertex": 0,
				"m_IndexCount": 15,
				"m_LocalAABB": {
					"m_Center": {
						"m_X": 0,
						"m_Y": 0,
						"m_Z": 0
					},
					"m_Extent": {
						"m_X": 0,
						"m_Y": 0,
						"m_Z": 0
					}
				},
				"m_Topology": 0,
				"m_VertexCount": 7
			}
		],
		"m_Texture": { "m_Collection": "cab-3c0b6d0158b163c9df24e66fb67aff1a", "m_PathID": -6999805533775363513 },
		"m_TextureRect": {
			"m_Height": 92,
			"m_Width": 169.96803,
			"m_X": 111.031975,
			"m_Y": 241
		},
		"m_TextureRectOffset": {
			"m_X": 0,
			"m_Y": 0
		},
		"m_UvTransform": {
			"m_W": 295,
			"m_X": 100,
			"m_Y": 271,
			"m_Z": 100
		},
		"m_VertexData": {
			"m_Channels": [
				{
					"m_Dimension": 3,
					"m_Format": 0,
					"m_Offset": 0,
					"m_Stream": 0
				},
				{
					"m_Dimension": 0,
					"m_Format": 0,
					"m_Offset": 0,
					"m_Stream": 0
				},
				{
					"m_Dimension": 0,
					"m_Format": 0,
					"m_Offset": 0,
					"m_Stream": 0
				},
				{
					"m_Dimension": 0,
					"m_Format": 0,
					"m_Offset": 0,
					"m_Stream": 0
				},
				{
					"m_Dimension": 2,
					"m_Format": 0,
					"m_Offset": 0,
					"m_Stream": 1
				},
				{
					"m_Dimension": 0,
					"m_Format": 0,
					"m_Offset": 0,
					"m_Stream": 0
				},
				{
					"m_Dimension": 0,
					"m_Format": 0,
					"m_Offset": 0,
					"m_Stream": 0
				},
				{
					"m_Dimension": 0,
					"m_Format": 0,
					"m_Offset": 0,
					"m_Stream": 0
				},
				{
					"m_Dimension": 0,
					"m_Format": 0,
					"m_Offset": 0,
					"m_Stream": 0
				},
				{
					"m_Dimension": 0,
					"m_Format": 0,
					"m_Offset": 0,
					"m_Stream": 0
				},
				{
					"m_Dimension": 0,
					"m_Format": 0,
					"m_Offset": 0,
					"m_Stream": 0
				},
				{
					"m_Dimension": 0,
					"m_Format": 0,
					"m_Offset": 0,
					"m_Stream": 0
				},
				{
					"m_Dimension": 0,
					"m_Format": 0,
					"m_Offset": 0,
					"m_Stream": 0
				},
				{
					"m_Dimension": 0,
					"m_Format": 0,
					"m_Offset": 0,
					"m_Stream": 0
				}
			],
			"m_Data": "j8L1POF6lD4AAAAAzMzMPSlcD74AAAAAj8J1v5mZGb4AAAAAFK6Hv3A9Cr8AAAAAuB7Fv9ej8L4AAAAAexTOvwrXIz0AAAAAPQq3v1yPwj4AAAAAAAAAAAAAAAAAAAAAAAAAAAAAAAAAAAAAAAAAAAAAAAAAAAAAAAAAAAAAAAAAAAAAAAAAAAAAAAAAAAAAAAAAAAAAAAA=",
			"m_VertexCount": 7
		}
	},
	"m_Rect": {
		"m_Height": 92,
		"m_Width": 169.96803,
		"m_X": 111.031975,
		"m_Y": 241
	},
	"m_RenderDataKey": {
		"Key": {
			"m_Data_0_": 1492562635,
			"m_Data_1_": 1115280509,
			"m_Data_2_": 1189360262,
			"m_Data_3_": 1965740860
		},
		"Value": 1351946299975302177
	},
	"m_SpriteAtlas": { "m_Collection": "cab-3c0b6d0158b163c9df24e66fb67aff1a", "m_PathID": 0 },
	"m_SpriteID": ""
}