{
	"m_AtlasName": "",
	"m_AtlasRD": {
		"m_AlphaTexture": { "m_Collection": "sharedassets2.assets", "m_PathID": 0 },
		"m_AtlasRectOffset": {
			"m_X": 0,
			"m_Y": 0
		},
		"m_Bindpose": [
			
		],
		"m_DownscaleMultiplier": 0,
		"m_IndexBuffer": "",
		"m_SecondaryTextures": [
			
		],
		"m_SettingsRaw": 0,
		"m_SubMeshes": [
			
		],
		"m_Texture": { "m_Collection": "sharedassets2.assets", "m_PathID": 0 },
		"m_TextureRect": {
			"m_Height": 0,
			"m_Width": 0,
			"m_X": 0,
			"m_Y": 0
		},
		"m_TextureRectOffset": {
			"m_X": 0,
			"m_Y": 0
		},
		"m_UvTransform": {
			"m_W": 0,
			"m_X": 0,
			"m_Y": 0,
			"m_Z": 0
		},
		"m_VertexData": {
			"m_Channels": [
				
			],
			"m_Data": "",
			"m_VertexCount": 0
		}
	},
	"m_AtlasTags": [
		
	],
	"m_Bones": [
		
	],
	"m_Border": {
		"m_W": 0,
		"m_X": 0,
		"m_Y": 0,
		"m_Z": 0
	},
	"m_CorrespondingSourceObject": { "m_Collection": "sharedassets2.assets", "m_PathID": 0 },
	"m_Extrude": 1,
	"m_HideFlags": 0,
	"m_IsPolygon": false,
	"m_Name": "hors_guardianangel0021",
	"m_Offset": {
		"m_X": -17.80427,
		"m_Y": 76.14589
	},
	"m_PackingTag": "",
	"m_PhysicsShape": [
		[
			{
				"m_X": -0.34710932,
				"m_Y": -2.0642784
			},
			{
				"m_X": -0.12796868,
				"m_Y": -2.0642784
			},
			{
				"m_X": 0.04734382,
				"m_Y": -1.921837
			},
			{
				"m_X": 0.102128975,
				"m_Y": -1.7574816
			},
			{
				"m_X": 0.18978523,
				"m_Y": -1.6040831
			},
			{
				"m_X": 0.33222663,
				"m_Y": -1.8341807
			},
			{
				"m_X": 0.3541407,
				"m_Y": -2.0533214
			},
			{
				"m_X": 0.51849616,
				"m_Y": -2.1628916
			},
			{
				"m_X": 0.8800782,
				"m_Y": -2.1519346
			},
			{
				"m_X": 1.0225196,
				"m_Y": -2.0861924
			},
			{
				"m_X": 1.0992188,
				"m_Y": -1.9875792
			},
			{
				"m_X": 1.0992188,
				"m_Y": -1.888966
			},
			{
				"m_X": 1.13209,
				"m_Y": -1.6479112
			},
			{
				"m_X": 1.143047,
				"m_Y": -1.8341807
			},
			{
				"m_X": 1.1978321,
				"m_Y": -1.9656651
			},
			{
				"m_X": 1.2635744,
				"m_Y": -2.0094934
			},
			{
				"m_X": 1.4169728,
				"m_Y": -2.0314074
			},
			{
				"m_X": 1.6141993,
				"m_Y": -2.0314074
			},
			{
				"m_X": 1.7128127,
				"m_Y": -1.9985362
			},
			{
				"m_X": 1.7895118,
				"m_Y": -1.9327941
			},
			{
				"m_X": 1.877168,
				"m_Y": -1.7793956
			},
			{
				"m_X": 1.9648243,
				"m_Y": -1.2534581
			},
			{
				"m_X": 1.9867384,
				"m_Y": -1.0014464
			},
			{
				"m_X": 1.9757813,
				"m_Y": -0.95761824
			},
			{
				"m_X": 2.1401367,
				"m_Y": -1.231544
			},
			{
				"m_X": 2.173008,
				"m_Y": -1.4287705
			},
			{
				"m_X": 2.227793,
				"m_Y": -1.4945128
			},
			{
				"m_X": 2.3702345,
				"m_Y": -1.6259972
			},
			{
				"m_X": 2.53459,
				"m_Y": -1.6588683
			},
			{
				"m_X": 2.6989455,
				"m_Y": -1.6259972
			},
			{
				"m_X": 2.8304298,
				"m_Y": -1.4397277
			},
			{
				"m_X": 2.8304298,
				"m_Y": -1.1877159
			},
			{
				"m_X": 2.7537305,
				"m_Y": -0.9904893
			},
			{
				"m_X": 2.3811915,
				"m_Y": -0.62890726
			},
			{
				"m_X": 2.0196095,
				"m_Y": -0.40976667
			},
			{
				"m_X": 2.0743947,
				"m_Y": -0.3221104
			},
			{
				"m_X": 2.0743947,
				"m_Y": -0.059141655
			},
			{
				"m_X": 2.0196095,
				"m_Y": 0.12712789
			},
			{
				"m_X": 1.877168,
				"m_Y": 0.24765523
			},
			{
				"m_X": 1.5703712,
				"m_Y": 0.521581
			},
			{
				"m_X": 1.4279298,
				"m_Y": 0.5873232
			},
			{
				"m_X": 1.2416602,
				"m_Y": 0.6530654
			},
			{
				"m_X": 0.814336,
				"m_Y": 0.6530654
			},
			{
				"m_X": 0.71572274,
				"m_Y": 0.6201943
			},
			{
				"m_X": 0.5513673,
				"m_Y": 0.53253806
			},
			{
				"m_X": 0.44179696,
				"m_Y": 0.4120107
			},
			{
				"m_X": 0.34318367,
				"m_Y": 0.14904195
			},
			{
				"m_X": 0.29935554,
				"m_Y": -0.081055716
			},
			{
				"m_X": 0.16787116,
				"m_Y": -0.21254009
			},
			{
				"m_X": -0.8182617,
				"m_Y": -0.20158306
			},
			{
				"m_X": -1.0374023,
				"m_Y": -0.22349712
			},
			{
				"m_X": -1.2565429,
				"m_Y": -0.11392681
			},
			{
				"m_X": -1.5085547,
				"m_Y": -0.13584088
			},
			{
				"m_X": -1.5523828,
				"m_Y": -0.16871198
			},
			{
				"m_X": -1.7605664,
				"m_Y": -0.36593854
			},
			{
				"m_X": -1.8372656,
				"m_Y": -0.4974229
			},
			{
				"m_X": -1.8810937,
				"m_Y": -0.6398643
			},
			{
				"m_X": -1.8920507,
				"m_Y": -0.69464946
			},
			{
				"m_X": -1.9139649,
				"m_Y": -0.9685753
			},
			{
				"m_X": -1.9030077,
				"m_Y": -1.1658019
			},
			{
				"m_X": -1.8482226,
				"m_Y": -1.4616417
			},
			{
				"m_X": -2.1659765,
				"m_Y": -1.4287705
			},
			{
				"m_X": -2.330332,
				"m_Y": -1.4397277
			},
			{
				"m_X": -2.3960743,
				"m_Y": -1.4397277
			},
			{
				"m_X": -2.4399023,
				"m_Y": -1.5164268
			},
			{
				"m_X": -2.4399023,
				"m_Y": -1.593126
			},
			{
				"m_X": -2.2755468,
				"m_Y": -1.7574816
			},
			{
				"m_X": -2.0673633,
				"m_Y": -1.888966
			},
			{
				"m_X": -1.8810937,
				"m_Y": -1.9766222
			},
			{
				"m_X": -1.5852538,
				"m_Y": -1.9985362
			},
			{
				"m_X": -1.2455859,
				"m_Y": -2.2943761
			},
			{
				"m_X": -1.1360155,
				"m_Y": -2.3272471
			},
			{
				"m_X": -0.927832,
				"m_Y": -2.3272471
			},
			{
				"m_X": -0.7415624,
				"m_Y": -2.239591
			},
			{
				"m_X": -0.46763667,
				"m_Y": -2.0423644
			}
		],
		[
			{
				"m_X": -1.1579297,
				"m_Y": -2.1081066
			},
			{
				"m_X": -1.2127148,
				"m_Y": -2.0423644
			},
			{
				"m_X": -1.289414,
				"m_Y": -1.9656651
			},
			{
				"m_X": -1.3332422,
				"m_Y": -1.9327941
			},
			{
				"m_X": -1.4428124,
				"m_Y": -1.8670518
			},
			{
				"m_X": -1.596211,
				"m_Y": -1.8122667
			},
			{
				"m_X": -1.7276952,
				"m_Y": -1.7793956
			},
			{
				"m_X": -1.8263086,
				"m_Y": -1.7684386
			},
			{
				"m_X": -1.8701367,
				"m_Y": -1.7574816
			},
			{
				"m_X": -2.001621,
				"m_Y": -1.7026963
			},
			{
				"m_X": -2.0454493,
				"m_Y": -1.6698253
			},
			{
				"m_X": -2.0564063,
				"m_Y": -1.6698253
			},
			{
				"m_X": -2.1221485,
				"m_Y": -1.6150402
			},
			{
				"m_X": -2.1440625,
				"m_Y": -1.6259972
			},
			{
				"m_X": -1.8263086,
				"m_Y": -1.6479112
			},
			{
				"m_X": -1.7605664,
				"m_Y": -1.6369542
			},
			{
				"m_X": -1.6838672,
				"m_Y": -1.6150402
			},
			{
				"m_X": -1.5523828,
				"m_Y": -1.5602549
			},
			{
				"m_X": -1.5085547,
				"m_Y": -1.5273839
			},
			{
				"m_X": -1.3989843,
				"m_Y": -1.4068565
			},
			{
				"m_X": -1.3441992,
				"m_Y": -1.2753721
			},
			{
				"m_X": -1.311328,
				"m_Y": -1.1767589
			},
			{
				"m_X": -1.311328,
				"m_Y": -1.0891026
			},
			{
				"m_X": -1.289414,
				"m_Y": -1.0452745
			},
			{
				"m_X": -1.278457,
				"m_Y": -0.9685753
			},
			{
				"m_X": -1.2674999,
				"m_Y": -0.8370909
			},
			{
				"m_X": -1.2565429,
				"m_Y": -0.74943465
			},
			{
				"m_X": -1.2346289,
				"m_Y": -0.68369246
			},
			{
				"m_X": -1.1908008,
				"m_Y": -0.5960362
			},
			{
				"m_X": -1.1469727,
				"m_Y": -0.54125106
			},
			{
				"m_X": -1.1141015,
				"m_Y": -0.530294
			},
			{
				"m_X": -1.0483593,
				"m_Y": -0.4974229
			},
			{
				"m_X": -0.9607031,
				"m_Y": -0.43168074
			},
			{
				"m_X": -0.8949609,
				"m_Y": -0.4207237
			},
			{
				"m_X": -0.8182617,
				"m_Y": -0.40976667
			},
			{
				"m_X": -0.8073046,
				"m_Y": -0.39880964
			},
			{
				"m_X": -0.4785937,
				"m_Y": -0.39880964
			},
			{
				"m_X": -0.46763667,
				"m_Y": -0.3878526
			},
			{
				"m_X": 0.014472725,
				"m_Y": -0.3878526
			},
			{
				"m_X": 0.025429755,
				"m_Y": -0.39880964
			},
			{
				"m_X": 0.16787116,
				"m_Y": -0.39880964
			},
			{
				"m_X": 0.21169929,
				"m_Y": -0.3878526
			},
			{
				"m_X": 0.2883985,
				"m_Y": -0.3549815
			},
			{
				"m_X": 0.4198829,
				"m_Y": -0.21254009
			},
			{
				"m_X": 0.46371102,
				"m_Y": -0.15775494
			},
			{
				"m_X": 0.49658212,
				"m_Y": -0.081055716
			},
			{
				"m_X": 0.51849616,
				"m_Y": -0.026270559
			},
			{
				"m_X": 0.5404102,
				"m_Y": 0.06138569
			},
			{
				"m_X": 0.5513673,
				"m_Y": 0.15999898
			},
			{
				"m_X": 0.6280665,
				"m_Y": 0.3133974
			},
			{
				"m_X": 0.6828517,
				"m_Y": 0.36818257
			},
			{
				"m_X": 0.8800782,
				"m_Y": 0.45583883
			},
			{
				"m_X": 0.9239063,
				"m_Y": 0.45583883
			},
			{
				"m_X": 0.9348634,
				"m_Y": 0.46679586
			},
			{
				"m_X": 1.143047,
				"m_Y": 0.46679586
			},
			{
				"m_X": 1.154004,
				"m_Y": 0.45583883
			},
			{
				"m_X": 1.2854884,
				"m_Y": 0.42296773
			},
			{
				"m_X": 1.3402735,
				"m_Y": 0.39009663
			},
			{
				"m_X": 1.493672,
				"m_Y": 0.30244038
			},
			{
				"m_X": 1.2087891,
				"m_Y": 0.3133974
			},
			{
				"m_X": 1.13209,
				"m_Y": 0.30244038
			},
			{
				"m_X": 1.0882618,
				"m_Y": 0.29148334
			},
			{
				"m_X": 1.0225196,
				"m_Y": 0.26956928
			},
			{
				"m_X": 0.9458204,
				"m_Y": 0.2366982
			},
			{
				"m_X": 0.82529306,
				"m_Y": 0.11617085
			},
			{
				"m_X": 0.78146493,
				"m_Y": 0.017557567
			},
			{
				"m_X": 0.7705079,
				"m_Y": -0.03722759
			},
			{
				"m_X": 0.7705079,
				"m_Y": -0.24541119
			},
			{
				"m_X": 0.78146493,
				"m_Y": -0.33306745
			},
			{
				"m_X": 0.803379,
				"m_Y": -0.40976667
			},
			{
				"m_X": 0.83625007,
				"m_Y": -0.47550884
			},
			{
				"m_X": 0.9458204,
				"m_Y": -0.57412213
			},
			{
				"m_X": 1.0553907,
				"m_Y": -0.61795026
			},
			{
				"m_X": 1.143047,
				"m_Y": -0.6398643
			},
			{
				"m_X": 1.2197462,
				"m_Y": -0.6508213
			},
			{
				"m_X": 1.526543,
				"m_Y": -0.6508213
			},
			{
				"m_X": 1.6141993,
				"m_Y": -0.6398643
			},
			{
				"m_X": 1.6689845,
				"m_Y": -0.62890726
			},
			{
				"m_X": 1.7347267,
				"m_Y": -0.60699326
			},
			{
				"m_X": 1.7456837,
				"m_Y": -0.6617784
			},
			{
				"m_X": 1.7895118,
				"m_Y": -0.74943465
			},
			{
				"m_X": 1.7895118,
				"m_Y": -0.95761824
			},
			{
				"m_X": 1.7785548,
				"m_Y": -0.9685753
			},
			{
				"m_X": 1.7675978,
				"m_Y": -1.0671885
			},
			{
				"m_X": 1.7456837,
				"m_Y": -1.242501
			},
			{
				"m_X": 1.7347267,
				"m_Y": -1.3630284
			},
			{
				"m_X": 1.7237697,
				"m_Y": -1.4616417
			},
			{
				"m_X": 1.6799415,
				"m_Y": -1.6698253
			},
			{
				"m_X": 1.6470704,
				"m_Y": -1.8013097
			},
			{
				"m_X": 1.5813283,
				"m_Y": -1.8451378
			},
			{
				"m_X": 1.4060158,
				"m_Y": -1.8341807
			},
			{
				"m_X": 1.3402735,
				"m_Y": -1.7903526
			},
			{
				"m_X": 1.3402735,
				"m_Y": -1.7355675
			},
			{
				"m_X": 1.3293165,
				"m_Y": -1.7246104
			},
			{
				"m_X": 1.3293165,
				"m_Y": -1.4616417
			},
			{
				"m_X": 1.3183595,
				"m_Y": -1.4287705
			},
			{
				"m_X": 1.2854884,
				"m_Y": -1.3849424
			},
			{
				"m_X": 1.1759181,
				"m_Y": -1.3958995
			},
			{
				"m_X": 1.164961,
				"m_Y": -1.4287705
			},
			{
				"m_X": 1.0444337,
				"m_Y": -1.4178135
			},
			{
				"m_X": 0.9896485,
				"m_Y": -1.4178135
			},
			{
				"m_X": 0.9348634,
				"m_Y": -1.4506847
			},
			{
				"m_X": 0.9239063,
				"m_Y": -1.4835558
			},
			{
				"m_X": 0.9239063,
				"m_Y": -1.8670518
			},
			{
				"m_X": 0.9129493,
				"m_Y": -1.8780088
			},
			{
				"m_X": 0.85816413,
				"m_Y": -1.9656651
			},
			{
				"m_X": 0.803379,
				"m_Y": -1.9656651
			},
			{
				"m_X": 0.7266798,
				"m_Y": -1.9766222
			},
			{
				"m_X": 0.6061524,
				"m_Y": -1.9875792
			},
			{
				"m_X": 0.5951954,
				"m_Y": -1.9766222
			},
			{
				"m_X": 0.5294532,
				"m_Y": -1.9547081
			},
			{
				"m_X": 0.5294532,
				"m_Y": -1.899923
			},
			{
				"m_X": 0.51849616,
				"m_Y": -1.8122667
			},
			{
				"m_X": 0.50753915,
				"m_Y": -1.6917393
			},
			{
				"m_X": 0.49658212,
				"m_Y": -1.6807823
			},
			{
				"m_X": 0.49658212,
				"m_Y": -1.5054698
			},
			{
				"m_X": 0.4856251,
				"m_Y": -1.3958995
			},
			{
				"m_X": 0.47466806,
				"m_Y": -1.3630284
			},
			{
				"m_X": 0.4198829,
				"m_Y": -1.3082433
			},
			{
				"m_X": 0.3541407,
				"m_Y": -1.2972863
			},
			{
				"m_X": 0.2883985,
				"m_Y": -1.3958995
			},
			{
				"m_X": 0.29935554,
				"m_Y": -1.4068565
			},
			{
				"m_X": 0.18978523,
				"m_Y": -1.4068565
			},
			{
				"m_X": 0.102128975,
				"m_Y": -1.4178135
			},
			{
				"m_X": 0.0035156931,
				"m_Y": -1.4945128
			},
			{
				"m_X": -0.051269464,
				"m_Y": -1.571212
			},
			{
				"m_X": -0.095097594,
				"m_Y": -1.6588683
			},
			{
				"m_X": -0.08414056,
				"m_Y": -1.7246104
			},
			{
				"m_X": -0.16083978,
				"m_Y": -1.8451378
			},
			{
				"m_X": -0.19371088,
				"m_Y": -1.8670518
			},
			{
				"m_X": -0.36902338,
				"m_Y": -1.8670518
			},
			{
				"m_X": -0.37998042,
				"m_Y": -1.8560948
			},
			{
				"m_X": -0.45667964,
				"m_Y": -1.8560948
			},
			{
				"m_X": -0.52242184,
				"m_Y": -1.8670518
			},
			{
				"m_X": -0.58816403,
				"m_Y": -1.888966
			},
			{
				"m_X": -0.64294916,
				"m_Y": -1.91088
			},
			{
				"m_X": -0.77443355,
				"m_Y": -2.0094934
			},
			{
				"m_X": -0.91687495,
				"m_Y": -2.1081066
			},
			{
				"m_X": -0.938789,
				"m_Y": -2.1081066
			},
			{
				"m_X": -1.0045313,
				"m_Y": -2.1300206
			},
			{
				"m_X": -1.0154883,
				"m_Y": -2.1409776
			},
			{
				"m_X": -1.1031445,
				"m_Y": -2.1300206
			}
		],
		[
			{
				"m_X": 0.18978523,
				"m_Y": -1.0562315
			},
			{
				"m_X": 0.50753915,
				"m_Y": -0.6617784
			},
			{
				"m_X": 0.5294532,
				"m_Y": -0.5631651
			},
			{
				"m_X": 0.5294532,
				"m_Y": -0.4207237
			},
			{
				"m_X": 0.46371102,
				"m_Y": -0.33306745
			},
			{
				"m_X": 0.3212696,
				"m_Y": -0.33306745
			},
			{
				"m_X": 0.27744147,
				"m_Y": -0.34402448
			},
			{
				"m_X": 0.036386788,
				"m_Y": -0.4645518
			},
			{
				"m_X": -0.24849603,
				"m_Y": -0.6727354
			},
			{
				"m_X": -0.52242184,
				"m_Y": -1.0124034
			},
			{
				"m_X": -0.56624997,
				"m_Y": -1.0891026
			},
			{
				"m_X": -0.56624997,
				"m_Y": -1.3301573
			},
			{
				"m_X": -0.5443359,
				"m_Y": -1.4397277
			},
			{
				"m_X": -0.4128515,
				"m_Y": -1.571212
			},
			{
				"m_X": -0.34710932,
				"m_Y": -1.582169
			},
			{
				"m_X": -0.14988275,
				"m_Y": -1.582169
			},
			{
				"m_X": -0.07318353,
				"m_Y": -1.571212
			},
			{
				"m_X": 0.102128975,
				"m_Y": -1.3849424
			},
			{
				"m_X": 0.12404304,
				"m_Y": -1.2863292
			}
		],
		[
			{
				"m_X": 2.4140627,
				"m_Y": -1.4287705
			},
			{
				"m_X": 2.4140627,
				"m_Y": -1.3958995
			},
			{
				"m_X": 2.4031055,
				"m_Y": -1.3849424
			},
			{
				"m_X": 2.4031055,
				"m_Y": -1.3520714
			},
			{
				"m_X": 2.3921485,
				"m_Y": -1.3411143
			},
			{
				"m_X": 2.3921485,
				"m_Y": -1.2753721
			},
			{
				"m_X": 2.3811915,
				"m_Y": -1.2644151
			},
			{
				"m_X": 2.3702345,
				"m_Y": -1.20963
			},
			{
				"m_X": 2.3592775,
				"m_Y": -1.1767589
			},
			{
				"m_X": 2.3154492,
				"m_Y": -1.1438878
			},
			{
				"m_X": 2.3044922,
				"m_Y": -1.1438878
			},
			{
				"m_X": 2.2716212,
				"m_Y": -1.1767589
			},
			{
				"m_X": 2.2825782,
				"m_Y": -1.1986729
			},
			{
				"m_X": 2.2935352,
				"m_Y": -1.1548448
			},
			{
				"m_X": 2.2825782,
				"m_Y": -1.1438878
			},
			{
				"m_X": 2.2825782,
				"m_Y": -1.1219738
			},
			{
				"m_X": 2.2497072,
				"m_Y": -1.0452745
			},
			{
				"m_X": 2.216836,
				"m_Y": -1.0233604
			},
			{
				"m_X": 2.216836,
				"m_Y": -1.0124034
			},
			{
				"m_X": 2.173008,
				"m_Y": -0.94666123
			},
			{
				"m_X": 2.151094,
				"m_Y": -0.89187604
			},
			{
				"m_X": 2.0963087,
				"m_Y": -0.8480479
			},
			{
				"m_X": 2.0963087,
				"m_Y": -0.8370909
			},
			{
				"m_X": 2.0634377,
				"m_Y": -0.8042198
			},
			{
				"m_X": 2.0634377,
				"m_Y": -0.7932628
			},
			{
				"m_X": 1.9976954,
				"m_Y": -0.7056065
			},
			{
				"m_X": 1.9867384,
				"m_Y": -0.69464946
			},
			{
				"m_X": 1.9867384,
				"m_Y": -0.6508213
			},
			{
				"m_X": 2.0524807,
				"m_Y": -0.69464946
			},
			{
				"m_X": 2.0743947,
				"m_Y": -0.7165635
			},
			{
				"m_X": 2.1072657,
				"m_Y": -0.7275206
			},
			{
				"m_X": 2.1401367,
				"m_Y": -0.74943465
			},
			{
				"m_X": 2.151094,
				"m_Y": -0.74943465
			},
			{
				"m_X": 2.162051,
				"m_Y": -0.7713487
			},
			{
				"m_X": 2.205879,
				"m_Y": -0.7932628
			},
			{
				"m_X": 2.2497072,
				"m_Y": -0.82613385
			},
			{
				"m_X": 2.2606642,
				"m_Y": -0.82613385
			},
			{
				"m_X": 2.3044922,
				"m_Y": -0.869962
			},
			{
				"m_X": 2.3154492,
				"m_Y": -0.869962
			},
			{
				"m_X": 2.4798048,
				"m_Y": -1.0343175
			},
			{
				"m_X": 2.4798048,
				"m_Y": -1.0452745
			},
			{
				"m_X": 2.512676,
				"m_Y": -1.0781456
			},
			{
				"m_X": 2.512676,
				"m_Y": -1.0891026
			},
			{
				"m_X": 2.556504,
				"m_Y": -1.1548448
			},
			{
				"m_X": 2.589375,
				"m_Y": -1.20963
			},
			{
				"m_X": 2.589375,
				"m_Y": -1.231544
			},
			{
				"m_X": 2.6003323,
				"m_Y": -1.242501
			},
			{
				"m_X": 2.6003323,
				"m_Y": -1.2644151
			},
			{
				"m_X": 2.6222463,
				"m_Y": -1.3082433
			},
			{
				"m_X": 2.6222463,
				"m_Y": -1.3958995
			},
			{
				"m_X": 2.6112893,
				"m_Y": -1.4068565
			},
			{
				"m_X": 2.589375,
				"m_Y": -1.4068565
			},
			{
				"m_X": 2.545547,
				"m_Y": -1.3411143
			},
			{
				"m_X": 2.545547,
				"m_Y": -1.3192003
			},
			{
				"m_X": 2.523633,
				"m_Y": -1.2863292
			},
			{
				"m_X": 2.523633,
				"m_Y": -1.2534581
			},
			{
				"m_X": 2.512676,
				"m_Y": -1.220587
			},
			{
				"m_X": 2.4031055,
				"m_Y": -1.0781456
			},
			{
				"m_X": 2.3592775,
				"m_Y": -1.0671885
			},
			{
				"m_X": 2.3264065,
				"m_Y": -1.1000596
			},
			{
				"m_X": 2.3264065,
				"m_Y": -1.1110166
			},
			{
				"m_X": 2.3592775,
				"m_Y": -1.1767589
			},
			{
				"m_X": 2.3592775,
				"m_Y": -1.20963
			},
			{
				"m_X": 2.4140627,
				"m_Y": -1.3192003
			},
			{
				"m_X": 2.4250197,
				"m_Y": -1.4068565
			},
			{
				"m_X": 2.4250197,
				"m_Y": -1.4397277
			}
		],
		[
			{
				"m_X": -1.6729101,
				"m_Y": -1.2972863
			},
			{
				"m_X": -1.6729101,
				"m_Y": -1.2644151
			},
			{
				"m_X": -1.6838672,
				"m_Y": -1.2534581
			},
			{
				"m_X": -1.6838672,
				"m_Y": -1.220587
			},
			{
				"m_X": -1.6948242,
				"m_Y": -1.20963
			},
			{
				"m_X": -1.6948242,
				"m_Y": -1.1658019
			},
			{
				"m_X": -1.7057812,
				"m_Y": -1.1548448
			},
			{
				"m_X": -1.7057812,
				"m_Y": -1.0562315
			},
			{
				"m_X": -1.7167382,
				"m_Y": -1.0452745
			},
			{
				"m_X": -1.7167382,
				"m_Y": -0.89187604
			},
			{
				"m_X": -1.7276952,
				"m_Y": -0.88091904
			},
			{
				"m_X": -1.7167382,
				"m_Y": -0.869962
			},
			{
				"m_X": -1.7167382,
				"m_Y": -0.7823057
			},
			{
				"m_X": -1.7057812,
				"m_Y": -0.7713487
			},
			{
				"m_X": -1.7057812,
				"m_Y": -0.7056065
			},
			{
				"m_X": -1.6948242,
				"m_Y": -0.69464946
			},
			{
				"m_X": -1.6729101,
				"m_Y": -0.60699326
			},
			{
				"m_X": -1.607168,
				"m_Y": -0.48646587
			},
			{
				"m_X": -1.5195117,
				"m_Y": -0.3878526
			},
			{
				"m_X": -1.4647266,
				"m_Y": -0.33306745
			},
			{
				"m_X": -1.4318554,
				"m_Y": -0.33306745
			},
			{
				"m_X": -1.4208984,
				"m_Y": -0.3221104
			},
			{
				"m_X": -1.3332422,
				"m_Y": -0.3221104
			},
			{
				"m_X": -1.311328,
				"m_Y": -0.31115338
			},
			{
				"m_X": -1.2127148,
				"m_Y": -0.36593854
			},
			{
				"m_X": -1.2127148,
				"m_Y": -0.3549815
			},
			{
				"m_X": -1.2455859,
				"m_Y": -0.3878526
			},
			{
				"m_X": -1.2565429,
				"m_Y": -0.3878526
			},
			{
				"m_X": -1.3551562,
				"m_Y": -0.48646587
			},
			{
				"m_X": -1.3551562,
				"m_Y": -0.4974229
			},
			{
				"m_X": -1.4099413,
				"m_Y": -0.5631651
			},
			{
				"m_X": -1.4318554,
				"m_Y": -0.6508213
			},
			{
				"m_X": -1.4537694,
				"m_Y": -0.68369246
			},
			{
				"m_X": -1.4537694,
				"m_Y": -0.7275206
			},
			{
				"m_X": -1.4647266,
				"m_Y": -0.7384776
			},
			{
				"m_X": -1.4647266,
				"m_Y": -0.82613385
			},
			{
				"m_X": -1.4866406,
				"m_Y": -0.8480479
			},
			{
				"m_X": -1.4975976,
				"m_Y": -0.9795323
			},
			{
				"m_X": -1.5085547,
				"m_Y": -0.9904893
			},
			{
				"m_X": -1.5085547,
				"m_Y": -1.1438878
			},
			{
				"m_X": -1.5304687,
				"m_Y": -1.1767589
			},
			{
				"m_X": -1.5304687,
				"m_Y": -1.20963
			},
			{
				"m_X": -1.5523828,
				"m_Y": -1.242501
			},
			{
				"m_X": -1.5523828,
				"m_Y": -1.2644151
			},
			{
				"m_X": -1.5742968,
				"m_Y": -1.2972863
			},
			{
				"m_X": -1.629082,
				"m_Y": -1.3630284
			},
			{
				"m_X": -1.6400391,
				"m_Y": -1.3520714
			}
		],
		[
			{
				"m_X": 1.1868751,
				"m_Y": -0.4207237
			},
			{
				"m_X": 1.1759181,
				"m_Y": -0.40976667
			},
			{
				"m_X": 1.143047,
				"m_Y": -0.40976667
			},
			{
				"m_X": 1.1101758,
				"m_Y": -0.3878526
			},
			{
				"m_X": 1.0882618,
				"m_Y": -0.3878526
			},
			{
				"m_X": 1.0663477,
				"m_Y": -0.36593854
			},
			{
				"m_X": 1.0553907,
				"m_Y": -0.36593854
			},
			{
				"m_X": 1.0225196,
				"m_Y": -0.3221104
			},
			{
				"m_X": 1.0006056,
				"m_Y": -0.28923932
			},
			{
				"m_X": 1.0006056,
				"m_Y": -0.26732525
			},
			{
				"m_X": 0.9896485,
				"m_Y": -0.25636822
			},
			{
				"m_X": 0.9896485,
				"m_Y": -0.21254009
			},
			{
				"m_X": 0.9786915,
				"m_Y": -0.20158306
			},
			{
				"m_X": 0.9786915,
				"m_Y": -0.10296978
			},
			{
				"m_X": 0.9896485,
				"m_Y": -0.09201275
			},
			{
				"m_X": 0.9896485,
				"m_Y": -0.048184622
			},
			{
				"m_X": 1.0006056,
				"m_Y": -0.03722759
			},
			{
				"m_X": 1.0115626,
				"m_Y": -0.004356497
			},
			{
				"m_X": 1.0444337,
				"m_Y": 0.03947163
			},
			{
				"m_X": 1.0553907,
				"m_Y": 0.03947163
			},
			{
				"m_X": 1.0992188,
				"m_Y": 0.07234272
			},
			{
				"m_X": 1.154004,
				"m_Y": 0.07234272
			},
			{
				"m_X": 1.164961,
				"m_Y": 0.083299756
			},
			{
				"m_X": 1.2416602,
				"m_Y": 0.083299756
			},
			{
				"m_X": 1.2526172,
				"m_Y": 0.09425679
			},
			{
				"m_X": 1.4388868,
				"m_Y": 0.10521382
			},
			{
				"m_X": 1.4169728,
				"m_Y": 0.083299756
			},
			{
				"m_X": 1.4169728,
				"m_Y": 0.0066005345
			},
			{
				"m_X": 1.4608009,
				"m_Y": -0.048184622
			},
			{
				"m_X": 1.493672,
				"m_Y": -0.07009868
			},
			{
				"m_X": 1.5703712,
				"m_Y": -0.07009868
			},
			{
				"m_X": 1.5813283,
				"m_Y": -0.081055716
			},
			{
				"m_X": 1.6141993,
				"m_Y": -0.081055716
			},
			{
				"m_X": 1.6251564,
				"m_Y": -0.09201275
			},
			{
				"m_X": 1.6908985,
				"m_Y": -0.10296978
			},
			{
				"m_X": 1.6908985,
				"m_Y": -0.124883845
			},
			{
				"m_X": 1.7018555,
				"m_Y": -0.13584088
			},
			{
				"m_X": 1.7018555,
				"m_Y": -0.16871198
			},
			{
				"m_X": 1.7128127,
				"m_Y": -0.17966901
			},
			{
				"m_X": 1.7128127,
				"m_Y": -0.22349712
			},
			{
				"m_X": 1.7237697,
				"m_Y": -0.23445415
			},
			{
				"m_X": 1.7237697,
				"m_Y": -0.28923932
			},
			{
				"m_X": 1.7347267,
				"m_Y": -0.30019635
			},
			{
				"m_X": 1.7347267,
				"m_Y": -0.36593854
			},
			{
				"m_X": 1.7456837,
				"m_Y": -0.37689558
			},
			{
				"m_X": 1.7237697,
				"m_Y": -0.3878526
			},
			{
				"m_X": 1.6908985,
				"m_Y": -0.3878526
			},
			{
				"m_X": 1.6799415,
				"m_Y": -0.39880964
			},
			{
				"m_X": 1.6470704,
				"m_Y": -0.39880964
			},
			{
				"m_X": 1.6361134,
				"m_Y": -0.40976667
			},
			{
				"m_X": 1.6032423,
				"m_Y": -0.40976667
			},
			{
				"m_X": 1.5922853,
				"m_Y": -0.4207237
			},
			{
				"m_X": 1.5375001,
				"m_Y": -0.4207237
			},
			{
				"m_X": 1.526543,
				"m_Y": -0.43168074
			},
			{
				"m_X": 1.2416602,
				"m_Y": -0.43168074
			},
			{
				"m_X": 1.2307032,
				"m_Y": -0.4207237
			}
		]
	],
	"m_Pivot": {
		"m_X": 0.46328115,
		"m_Y": 0.7769708
	},
	"m_PixelsToUnits": 91.265594,
	"m_PrefabAsset": { "m_Collection": "sharedassets2.assets", "m_PathID": 0 },
	"m_PrefabInstance": { "m_Collection": "sharedassets2.assets", "m_PathID": 0 },
	"m_RD": {
		"m_AlphaTexture": { "m_Collection": "sharedassets2.assets", "m_PathID": 0 },
		"m_AtlasRectOffset": {
			"m_X": -1,
			"m_Y": -1
		},
		"m_Bindpose": [
			
		],
		"m_DownscaleMultiplier": 1,
		"m_IndexBuffer": "FAAVABYAEQASABMAEwAKAAsAEAARABMADgAPABAADQAQABMADQAOABAACQAGAAcADQALAAwACwANABMAEwAJAAoAEwAUAAkACQAUAAYACQAHAAgAAgAGABQAAwAEAAUAAwAFAAYAAgADAAYAAAACABQAAAABAAIAAAAUABYA",
		"m_SecondaryTextures": [
			
		],
		"m_SettingsRaw": 64,
		"m_SubMeshes": [
			{
				"m_BaseVertex": 0,
				"m_FirstByte": 0,
				"m_FirstVertex": 0,
				"m_IndexCount": 63,
				"m_LocalAABB": {
					"m_Center": {
						"m_X": 0,
						"m_Y": 0,
						"m_Z": 0
					},
					"m_Extent": {
						"m_X": 0,
						"m_Y": 0,
						"m_Z": 0
					}
				},
				"m_Topology": 0,
				"m_VertexCount": 23
			}
		],
		"m_Texture": { "m_Collection": "sharedassets2.assets", "m_PathID": 89 },
		"m_TextureRect": {
			"m_Height": 274.9239,
			"m_Width": 484.88098,
			"m_X": 533.7809,
			"m_Y": 0.912854
		},
		"m_TextureRectOffset": {
			"m_X": 0,
			"m_Y": 0
		},
		"m_UvTransform": {
			"m_W": 214.52069,
			"m_X": 91.265594,
			"m_Y": 758.4171,
			"m_Z": 91.265594
		},
		"m_VertexData": {
			"m_Channels": [
				{
					"m_Dimension": 3,
					"m_Format": 0,
					"m_Offset": 0,
					"m_Stream": 0
				},
				{
					"m_Dimension": 0,
					"m_Format": 0,
					"m_Offset": 0,
					"m_Stream": 0
				},
				{
					"m_Dimension": 0,
					"m_Format": 0,
					"m_Offset": 0,
					"m_Stream": 0
				},
				{
					"m_Dimension": 0,
					"m_Format": 0,
					"m_Offset": 0,
					"m_Stream": 0
				},
				{
					"m_Dimension": 2,
					"m_Format": 0,
					"m_Offset": 0,
					"m_Stream": 1
				},
				{
					"m_Dimension": 0,
					"m_Format": 0,
					"m_Offset": 0,
					"m_Stream": 0
				},
				{
					"m_Dimension": 0,
					"m_Format": 0,
					"m_Offset": 0,
					"m_Stream": 0
				},
				{
					"m_Dimension": 0,
					"m_Format": 0,
					"m_Offset": 0,
					"m_Stream": 0
				},
				{
					"m_Dimension": 0,
					"m_Format": 0,
					"m_Offset": 0,
					"m_Stream": 0
				},
				{
					"m_Dimension": 0,
					"m_Format": 0,
					"m_Offset": 0,
					"m_Stream": 0
				},
				{
					"m_Dimension": 0,
					"m_Format": 0,
					"m_Offset": 0,
					"m_Stream": 0
				},
				{
					"m_Dimension": 0,
					"m_Format": 0,
					"m_Offset": 0,
					"m_Stream": 0
				},
				{
					"m_Dimension": 0,
					"m_Format": 0,
					"m_Offset": 0,
					"m_Stream": 0
				},
				{
					"m_Dimension": 0,
					"m_Format": 0,
					"m_Offset": 0,
					"m_Stream": 0
				}
			],
			"m_Data": "uR7FPykcCj8AAAAAr0cBQHsUGT4AAAAAH4ULQBUu0r4AAAAA61E4QCj8kb8AAAAAXY8yQOEa178AAAAAMzMTQHu00L8AAAAAU7j+P/+for8AAAAAaGbmP66XAsAAAAAAbGbmPqTADsAAAAAAOlwPPlwv5b8AAAAADML1vABQAcAAAAAATrhev+HKFcAAAAAARuGav+HKFcAAAAAAj8K1v0gxDMAAAAAA4XoEwOAa978AAAAAR+EqwPXIvr8AAAAA6lH4v81sr78AAAAAPAr3vzuK4b4AAAAA//+/v//Wzb0AAAAAEq5Hv8nMYb4AAAAAOlwPPnwUQ74AAAAAuR4FP6wHHD8AAAAAK1yPP5GCMD8AAAAAAAAAAAAAAAAAAAAAAAAAAAAAAAAAAAAAAAAAAAAAAAAAAAAAAAAAAAAAAAAAAAAAAAAAAAAAAAAAAAAAAAAAAAAAAAAAAAAAAAAAAAAAAAAAAAAAAAAAAAAAAAAAAAAAAAAAAAAAAAAAAAAAAAAAAAAAAAAAAAAAAAAAAAAAAAAAAAAAAAAAAAAAAAAAAAAAAAAAAAAAAAAAAAAAAAAAAAAAAAAAAAAAAAAAAAAAAAAAAAAAAAAAAAAAAAAAAAAAAAAAAA==",
			"m_VertexCount": 23
		}
	},
	"m_Rect": {
		"m_Height": 274.9239,
		"m_Width": 484.88098,
		"m_X": 533.7809,
		"m_Y": 0.912854
	},
	"m_RenderDataKey": {
		"Key": {
			"m_Data_0_": 211064777,
			"m_Data_1_": 1236661936,
			"m_Data_2_": 1604620988,
			"m_Data_3_": 1263556805
		},
		"Value": -8490438229911570885
	},
	"m_SpriteAtlas": { "m_Collection": "sharedassets2.assets", "m_PathID": 0 },
	"m_SpriteID": ""
}