{
	"m_AtlasName": "",
	"m_AtlasRD": {
		"m_AlphaTexture": { "m_Collection": "sharedassets2.assets", "m_PathID": 0 },
		"m_AtlasRectOffset": {
			"m_X": 0,
			"m_Y": 0
		},
		"m_Bindpose": [
			
		],
		"m_DownscaleMultiplier": 0,
		"m_IndexBuffer": "",
		"m_SecondaryTextures": [
			
		],
		"m_SettingsRaw": 0,
		"m_SubMeshes": [
			
		],
		"m_Texture": { "m_Collection": "sharedassets2.assets", "m_PathID": 0 },
		"m_TextureRect": {
			"m_Height": 0,
			"m_Width": 0,
			"m_X": 0,
			"m_Y": 0
		},
		"m_TextureRectOffset": {
			"m_X": 0,
			"m_Y": 0
		},
		"m_UvTransform": {
			"m_W": 0,
			"m_X": 0,
			"m_Y": 0,
			"m_Z": 0
		},
		"m_VertexData": {
			"m_Channels": [
				
			],
			"m_Data": "",
			"m_VertexCount": 0
		}
	},
	"m_AtlasTags": [
		
	],
	"m_Bones": [
		
	],
	"m_Border": {
		"m_W": 0,
		"m_X": 0,
		"m_Y": 0,
		"m_Z": 0
	},
	"m_CorrespondingSourceObject": { "m_Collection": "sharedassets2.assets", "m_PathID": 0 },
	"m_Extrude": 1,
	"m_HideFlags": 0,
	"m_IsPolygon": false,
	"m_Name": "hors_guardianangel0004",
	"m_Offset": {
		"m_X": -34.399353,
		"m_Y": 53.937916
	},
	"m_PackingTag": "",
	"m_PhysicsShape": [
		[
			{
				"m_X": 0.20138627,
				"m_Y": -1.5040017
			},
			{
				"m_X": 0.3109566,
				"m_Y": -1.4053885
			},
			{
				"m_X": 0.3438277,
				"m_Y": -1.6793143
			},
			{
				"m_X": 0.36574176,
				"m_Y": -1.7998415
			},
			{
				"m_X": 0.43148395,
				"m_Y": -1.8765408
			},
			{
				"m_X": 0.54105425,
				"m_Y": -1.9203689
			},
			{
				"m_X": 0.84785116,
				"m_Y": -1.9203689
			},
			{
				"m_X": 0.99029255,
				"m_Y": -1.8546268
			},
			{
				"m_X": 1.0560347,
				"m_Y": -1.8107986
			},
			{
				"m_X": 1.0779488,
				"m_Y": -1.7779275
			},
			{
				"m_X": 1.1108199,
				"m_Y": -1.624529
			},
			{
				"m_X": 1.1546481,
				"m_Y": -1.6574001
			},
			{
				"m_X": 1.2313472,
				"m_Y": -1.7779275
			},
			{
				"m_X": 1.5819722,
				"m_Y": -1.8217556
			},
			{
				"m_X": 1.7244136,
				"m_Y": -1.7560134
			},
			{
				"m_X": 1.8230269,
				"m_Y": -1.6574001
			},
			{
				"m_X": 1.8778121,
				"m_Y": -1.5149587
			},
			{
				"m_X": 1.9435543,
				"m_Y": -1.1643337
			},
			{
				"m_X": 1.9764254,
				"m_Y": -0.7589236
			},
			{
				"m_X": 2.0421677,
				"m_Y": -0.5069118
			},
			{
				"m_X": 2.0969527,
				"m_Y": -0.47404075
			},
			{
				"m_X": 2.2722652,
				"m_Y": -0.3863845
			},
			{
				"m_X": 2.4475777,
				"m_Y": -0.3863845
			},
			{
				"m_X": 2.557148,
				"m_Y": -0.3206423
			},
			{
				"m_X": 2.7105465,
				"m_Y": -0.23298605
			},
			{
				"m_X": 2.8420308,
				"m_Y": -0.16724387
			},
			{
				"m_X": 2.907773,
				"m_Y": -0.079587616
			},
			{
				"m_X": 3.0502145,
				"m_Y": 0.18338114
			},
			{
				"m_X": 3.1269138,
				"m_Y": 0.35869366
			},
			{
				"m_X": 3.1269138,
				"m_Y": 0.46826395
			},
			{
				"m_X": 3.0283005,
				"m_Y": 0.5887913
			},
			{
				"m_X": 2.8420308,
				"m_Y": 0.6654905
			},
			{
				"m_X": 2.7653317,
				"m_Y": 0.6874046
			},
			{
				"m_X": 2.4366207,
				"m_Y": 0.6874046
			},
			{
				"m_X": 2.3160934,
				"m_Y": 0.6545335
			},
			{
				"m_X": 2.1188667,
				"m_Y": 0.5340062
			},
			{
				"m_X": 1.9764254,
				"m_Y": 0.38060772
			},
			{
				"m_X": 1.9106832,
				"m_Y": 0.45730692
			},
			{
				"m_X": 1.8120699,
				"m_Y": 0.5120921
			},
			{
				"m_X": 1.6477145,
				"m_Y": 0.70931864
			},
			{
				"m_X": 1.4614449,
				"m_Y": 0.829846
			},
			{
				"m_X": 1.2642183,
				"m_Y": 0.87367415
			},
			{
				"m_X": 1.1765621,
				"m_Y": 0.8955882
			},
			{
				"m_X": 0.79306597,
				"m_Y": 0.8955882
			},
			{
				"m_X": 0.6615816,
				"m_Y": 0.8517601
			},
			{
				"m_X": 0.53009725,
				"m_Y": 0.75314677
			},
			{
				"m_X": 0.43148395,
				"m_Y": 0.6654905
			},
			{
				"m_X": 0.32191363,
				"m_Y": 0.32582256
			},
			{
				"m_X": 0.1356441,
				"m_Y": 0.5340062
			},
			{
				"m_X": -0.050625443,
				"m_Y": 0.64357644
			},
			{
				"m_X": -0.16019575,
				"m_Y": 0.6764476
			},
			{
				"m_X": -0.49986374,
				"m_Y": 0.6874046
			},
			{
				"m_X": -0.598477,
				"m_Y": 0.6545335
			},
			{
				"m_X": -0.7847465,
				"m_Y": 0.5887913
			},
			{
				"m_X": -0.89431685,
				"m_Y": 0.45730692
			},
			{
				"m_X": -0.89431685,
				"m_Y": 0.3696507
			},
			{
				"m_X": -0.7847465,
				"m_Y": 0.10668192
			},
			{
				"m_X": -0.70804733,
				"m_Y": 0.01902567
			},
			{
				"m_X": -0.8614458,
				"m_Y": 0.01902567
			},
			{
				"m_X": -1.0367583,
				"m_Y": -0.0028883922
			},
			{
				"m_X": -1.1463286,
				"m_Y": 0.0628538
			},
			{
				"m_X": -1.255899,
				"m_Y": 0.11763895
			},
			{
				"m_X": -1.5079106,
				"m_Y": 0.11763895
			},
			{
				"m_X": -1.7818364,
				"m_Y": -0.112458706
			},
			{
				"m_X": -1.9023638,
				"m_Y": -0.3863845
			},
			{
				"m_X": -1.9242778,
				"m_Y": -0.60552514
			},
			{
				"m_X": -1.9023638,
				"m_Y": -0.93423605
			},
			{
				"m_X": -1.8694927,
				"m_Y": -1.0438064
			},
			{
				"m_X": -1.8366215,
				"m_Y": -1.1424197
			},
			{
				"m_X": -2.0557623,
				"m_Y": -1.0766774
			},
			{
				"m_X": -2.2310748,
				"m_Y": -1.0547634
			},
			{
				"m_X": -2.2968168,
				"m_Y": -1.0547634
			},
			{
				"m_X": -2.373516,
				"m_Y": -1.1205056
			},
			{
				"m_X": -2.373516,
				"m_Y": -1.2081618
			},
			{
				"m_X": -2.2201176,
				"m_Y": -1.3944314
			},
			{
				"m_X": -2.1872466,
				"m_Y": -1.5040017
			},
			{
				"m_X": -2.1543756,
				"m_Y": -1.591658
			},
			{
				"m_X": -2.0448053,
				"m_Y": -1.7121853
			},
			{
				"m_X": -1.9242778,
				"m_Y": -1.7779275
			},
			{
				"m_X": -1.7380083,
				"m_Y": -1.8107986
			},
			{
				"m_X": -1.3435552,
				"m_Y": -1.8217556
			},
			{
				"m_X": -1.1463286,
				"m_Y": -2.0189822
			},
			{
				"m_X": -1.0477153,
				"m_Y": -2.0628104
			},
			{
				"m_X": -0.6970903,
				"m_Y": -2.0628104
			},
			{
				"m_X": -0.60943407,
				"m_Y": -2.0518532
			},
			{
				"m_X": -0.51082075,
				"m_Y": -1.986111
			},
			{
				"m_X": -0.22593795,
				"m_Y": -1.6902713
			},
			{
				"m_X": 0.05894487,
				"m_Y": -1.6354861
			}
		],
		[
			{
				"m_X": -1.0038872,
				"m_Y": -1.8546268
			},
			{
				"m_X": -1.1572856,
				"m_Y": -1.7012283
			},
			{
				"m_X": -1.2339848,
				"m_Y": -1.6683571
			},
			{
				"m_X": -1.266856,
				"m_Y": -1.6574001
			},
			{
				"m_X": -1.3545122,
				"m_Y": -1.6354861
			},
			{
				"m_X": -1.4859966,
				"m_Y": -1.613572
			},
			{
				"m_X": -1.7270513,
				"m_Y": -1.613572
			},
			{
				"m_X": -1.7380083,
				"m_Y": -1.602615
			},
			{
				"m_X": -1.8147075,
				"m_Y": -1.591658
			},
			{
				"m_X": -1.9023638,
				"m_Y": -1.5807009
			},
			{
				"m_X": -1.99002,
				"m_Y": -1.4711306
			},
			{
				"m_X": -2.000977,
				"m_Y": -1.3944314
			},
			{
				"m_X": -2.022891,
				"m_Y": -1.3506032
			},
			{
				"m_X": -2.0667193,
				"m_Y": -1.2739041
			},
			{
				"m_X": -1.9352349,
				"m_Y": -1.3396462
			},
			{
				"m_X": -1.8585356,
				"m_Y": -1.3615603
			},
			{
				"m_X": -1.6832231,
				"m_Y": -1.3615603
			},
			{
				"m_X": -1.639395,
				"m_Y": -1.3506032
			},
			{
				"m_X": -1.5188676,
				"m_Y": -1.2958181
			},
			{
				"m_X": -1.4531255,
				"m_Y": -1.230076
			},
			{
				"m_X": -1.4202543,
				"m_Y": -1.2081618
			},
			{
				"m_X": -1.3654692,
				"m_Y": -1.0876346
			},
			{
				"m_X": -1.3216411,
				"m_Y": -0.98902124
			},
			{
				"m_X": -1.2997271,
				"m_Y": -0.8465798
			},
			{
				"m_X": -1.28877,
				"m_Y": -0.7479665
			},
			{
				"m_X": -1.277813,
				"m_Y": -0.6383962
			},
			{
				"m_X": -1.266856,
				"m_Y": -0.55073994
			},
			{
				"m_X": -1.2339848,
				"m_Y": -0.44116965
			},
			{
				"m_X": -1.2339848,
				"m_Y": -0.40829855
			},
			{
				"m_X": -1.1791997,
				"m_Y": -0.34255636
			},
			{
				"m_X": -1.1353716,
				"m_Y": -0.29872826
			},
			{
				"m_X": -1.0477153,
				"m_Y": -0.25490013
			},
			{
				"m_X": -0.94910204,
				"m_Y": -0.18915793
			},
			{
				"m_X": -0.927188,
				"m_Y": -0.18915793
			},
			{
				"m_X": -0.82857466,
				"m_Y": -0.16724387
			},
			{
				"m_X": -0.81761765,
				"m_Y": -0.15628684
			},
			{
				"m_X": -0.60943407,
				"m_Y": -0.15628684
			},
			{
				"m_X": -0.57656294,
				"m_Y": -0.18915793
			},
			{
				"m_X": -0.47794968,
				"m_Y": -0.24394308
			},
			{
				"m_X": -0.3464653,
				"m_Y": -0.28777122
			},
			{
				"m_X": -0.2807231,
				"m_Y": -0.37542745
			},
			{
				"m_X": -0.19306685,
				"m_Y": -0.40829855
			},
			{
				"m_X": -0.01775435,
				"m_Y": -0.39734152
			},
			{
				"m_X": -0.006797319,
				"m_Y": -0.40829855
			},
			{
				"m_X": 0.08085893,
				"m_Y": -0.44116965
			},
			{
				"m_X": 0.16851519,
				"m_Y": -0.5288259
			},
			{
				"m_X": 0.33287066,
				"m_Y": -0.5288259
			},
			{
				"m_X": 0.42052692,
				"m_Y": -0.4959548
			},
			{
				"m_X": 0.49722612,
				"m_Y": -0.41925558
			},
			{
				"m_X": 0.5081832,
				"m_Y": -0.3863845
			},
			{
				"m_X": 0.5191402,
				"m_Y": -0.33159932
			},
			{
				"m_X": 0.5191402,
				"m_Y": -0.211072
			},
			{
				"m_X": 0.5081832,
				"m_Y": -0.1782009
			},
			{
				"m_X": 0.442441,
				"m_Y": -0.10150167
			},
			{
				"m_X": 0.39861286,
				"m_Y": 0.008068639
			},
			{
				"m_X": 0.46435502,
				"m_Y": 0.08476786
			},
			{
				"m_X": 0.49722612,
				"m_Y": 0.16146708
			},
			{
				"m_X": 0.5191402,
				"m_Y": 0.21625224
			},
			{
				"m_X": 0.53009725,
				"m_Y": 0.28199443
			},
			{
				"m_X": 0.5520113,
				"m_Y": 0.40252176
			},
			{
				"m_X": 0.5848824,
				"m_Y": 0.46826395
			},
			{
				"m_X": 0.6177535,
				"m_Y": 0.5449632
			},
			{
				"m_X": 0.68349564,
				"m_Y": 0.6107054
			},
			{
				"m_X": 0.78210896,
				"m_Y": 0.6545335
			},
			{
				"m_X": 0.85880816,
				"m_Y": 0.6874046
			},
			{
				"m_X": 0.9464644,
				"m_Y": 0.69836164
			},
			{
				"m_X": 0.9574215,
				"m_Y": 0.70931864
			},
			{
				"m_X": 1.132734,
				"m_Y": 0.70931864
			},
			{
				"m_X": 1.1765621,
				"m_Y": 0.6874046
			},
			{
				"m_X": 1.2532613,
				"m_Y": 0.6654905
			},
			{
				"m_X": 1.2861325,
				"m_Y": 0.6654905
			},
			{
				"m_X": 1.4066597,
				"m_Y": 0.5887913
			},
			{
				"m_X": 1.4395308,
				"m_Y": 0.57783425
			},
			{
				"m_X": 1.472402,
				"m_Y": 0.5449632
			},
			{
				"m_X": 1.494316,
				"m_Y": 0.5449632
			},
			{
				"m_X": 1.2423043,
				"m_Y": 0.55592024
			},
			{
				"m_X": 1.143691,
				"m_Y": 0.5449632
			},
			{
				"m_X": 1.0889058,
				"m_Y": 0.5340062
			},
			{
				"m_X": 1.0231637,
				"m_Y": 0.5120921
			},
			{
				"m_X": 0.9464644,
				"m_Y": 0.479221
			},
			{
				"m_X": 0.85880816,
				"m_Y": 0.39156476
			},
			{
				"m_X": 0.804023,
				"m_Y": 0.31486553
			},
			{
				"m_X": 0.78210896,
				"m_Y": 0.26008037
			},
			{
				"m_X": 0.7711519,
				"m_Y": 0.22720927
			},
			{
				"m_X": 0.7711519,
				"m_Y": -0.04671652
			},
			{
				"m_X": 0.79306597,
				"m_Y": -0.1453298
			},
			{
				"m_X": 0.8259371,
				"m_Y": -0.22202902
			},
			{
				"m_X": 0.92455035,
				"m_Y": -0.3206423
			},
			{
				"m_X": 1.0450777,
				"m_Y": -0.37542745
			},
			{
				"m_X": 1.0889058,
				"m_Y": -0.3863845
			},
			{
				"m_X": 1.1875191,
				"m_Y": -0.40829855
			},
			{
				"m_X": 1.5600582,
				"m_Y": -0.40829855
			},
			{
				"m_X": 1.6258004,
				"m_Y": -0.39734152
			},
			{
				"m_X": 1.7244136,
				"m_Y": -0.37542745
			},
			{
				"m_X": 1.7791988,
				"m_Y": -0.48499778
			},
			{
				"m_X": 1.7901559,
				"m_Y": -0.4959548
			},
			{
				"m_X": 1.7901559,
				"m_Y": -0.71509546
			},
			{
				"m_X": 1.7791988,
				"m_Y": -0.72605246
			},
			{
				"m_X": 1.7682418,
				"m_Y": -0.8246658
			},
			{
				"m_X": 1.7463278,
				"m_Y": -0.9780642
			},
			{
				"m_X": 1.7353706,
				"m_Y": -1.0985916
			},
			{
				"m_X": 1.7134566,
				"m_Y": -1.262947
			},
			{
				"m_X": 1.6477145,
				"m_Y": -1.5587869
			},
			{
				"m_X": 1.5819722,
				"m_Y": -1.591658
			},
			{
				"m_X": 1.4176167,
				"m_Y": -1.602615
			},
			{
				"m_X": 1.4066597,
				"m_Y": -1.591658
			},
			{
				"m_X": 1.3409176,
				"m_Y": -1.5587869
			},
			{
				"m_X": 1.3299606,
				"m_Y": -1.4711306
			},
			{
				"m_X": 1.3299606,
				"m_Y": -1.3506032
			},
			{
				"m_X": 1.3190035,
				"m_Y": -1.2081618
			},
			{
				"m_X": 1.2642183,
				"m_Y": -1.1533767
			},
			{
				"m_X": 1.1875191,
				"m_Y": -1.1643337
			},
			{
				"m_X": 1.1108199,
				"m_Y": -1.1862478
			},
			{
				"m_X": 0.97933555,
				"m_Y": -1.1862478
			},
			{
				"m_X": 0.92455035,
				"m_Y": -1.230076
			},
			{
				"m_X": 0.92455035,
				"m_Y": -1.5807009
			},
			{
				"m_X": 0.91359335,
				"m_Y": -1.591658
			},
			{
				"m_X": 0.91359335,
				"m_Y": -1.6683571
			},
			{
				"m_X": 0.8916793,
				"m_Y": -1.7012283
			},
			{
				"m_X": 0.804023,
				"m_Y": -1.7231424
			},
			{
				"m_X": 0.74923784,
				"m_Y": -1.7340994
			},
			{
				"m_X": 0.73828083,
				"m_Y": -1.7450564
			},
			{
				"m_X": 0.5739254,
				"m_Y": -1.7450564
			},
			{
				"m_X": 0.5191402,
				"m_Y": -1.6902713
			},
			{
				"m_X": 0.5191402,
				"m_Y": -1.602615
			},
			{
				"m_X": 0.5081832,
				"m_Y": -1.4492166
			},
			{
				"m_X": 0.49722612,
				"m_Y": -1.4382595
			},
			{
				"m_X": 0.49722612,
				"m_Y": -1.262947
			},
			{
				"m_X": 0.4862691,
				"m_Y": -1.1643337
			},
			{
				"m_X": 0.47531205,
				"m_Y": -1.1205056
			},
			{
				"m_X": 0.43148395,
				"m_Y": -1.0766774
			},
			{
				"m_X": 0.3766988,
				"m_Y": -1.0657204
			},
			{
				"m_X": 0.2780855,
				"m_Y": -1.1643337
			},
			{
				"m_X": 0.11373003,
				"m_Y": -1.1862478
			},
			{
				"m_X": 0.047987837,
				"m_Y": -1.25199
			},
			{
				"m_X": 0.047987837,
				"m_Y": -1.3834743
			},
			{
				"m_X": -0.006797319,
				"m_Y": -1.4273025
			},
			{
				"m_X": -0.08349654,
				"m_Y": -1.4492166
			},
			{
				"m_X": -0.08349654,
				"m_Y": -1.4601736
			},
			{
				"m_X": -0.22593795,
				"m_Y": -1.4711306
			},
			{
				"m_X": -0.30263716,
				"m_Y": -1.5040017
			},
			{
				"m_X": -0.36837935,
				"m_Y": -1.5478299
			},
			{
				"m_X": -0.51082075,
				"m_Y": -1.6902713
			},
			{
				"m_X": -0.60943407,
				"m_Y": -1.8217556
			},
			{
				"m_X": -0.70804733,
				"m_Y": -1.8655838
			},
			{
				"m_X": -0.7628325,
				"m_Y": -1.8765408
			},
			{
				"m_X": -0.9052739,
				"m_Y": -1.8874978
			},
			{
				"m_X": -0.9162309,
				"m_Y": -1.8765408
			}
		],
		[
			{
				"m_X": -1.6613091,
				"m_Y": -1.0876346
			},
			{
				"m_X": -1.6722661,
				"m_Y": -1.0328493
			},
			{
				"m_X": -1.6832231,
				"m_Y": -1.0218923
			},
			{
				"m_X": -1.6832231,
				"m_Y": -0.98902124
			},
			{
				"m_X": -1.6941801,
				"m_Y": -0.9780642
			},
			{
				"m_X": -1.6941801,
				"m_Y": -0.92327905
			},
			{
				"m_X": -1.7051373,
				"m_Y": -0.912322
			},
			{
				"m_X": -1.7051373,
				"m_Y": -0.8246658
			},
			{
				"m_X": -1.7160943,
				"m_Y": -0.8137087
			},
			{
				"m_X": -1.7160943,
				"m_Y": -0.64935327
			},
			{
				"m_X": -1.7270513,
				"m_Y": -0.6383962
			},
			{
				"m_X": -1.7160943,
				"m_Y": -0.6274392
			},
			{
				"m_X": -1.7160943,
				"m_Y": -0.53978294
			},
			{
				"m_X": -1.7051373,
				"m_Y": -0.5288259
			},
			{
				"m_X": -1.7051373,
				"m_Y": -0.4630837
			},
			{
				"m_X": -1.6832231,
				"m_Y": -0.41925558
			},
			{
				"m_X": -1.6832231,
				"m_Y": -0.3863845
			},
			{
				"m_X": -1.6065239,
				"m_Y": -0.24394308
			},
			{
				"m_X": -1.4640825,
				"m_Y": -0.09054464
			},
			{
				"m_X": -1.3983403,
				"m_Y": -0.09054464
			},
			{
				"m_X": -1.3873833,
				"m_Y": -0.079587616
			},
			{
				"m_X": -1.2997271,
				"m_Y": -0.079587616
			},
			{
				"m_X": -1.28877,
				"m_Y": -0.09054464
			},
			{
				"m_X": -1.266856,
				"m_Y": -0.09054464
			},
			{
				"m_X": -1.2339848,
				"m_Y": -0.112458706
			},
			{
				"m_X": -1.2120708,
				"m_Y": -0.12341574
			},
			{
				"m_X": -1.2120708,
				"m_Y": -0.112458706
			},
			{
				"m_X": -1.2449418,
				"m_Y": -0.1453298
			},
			{
				"m_X": -1.255899,
				"m_Y": -0.1453298
			},
			{
				"m_X": -1.3654692,
				"m_Y": -0.25490013
			},
			{
				"m_X": -1.3654692,
				"m_Y": -0.26585716
			},
			{
				"m_X": -1.3873833,
				"m_Y": -0.28777122
			},
			{
				"m_X": -1.3873833,
				"m_Y": -0.29872826
			},
			{
				"m_X": -1.4202543,
				"m_Y": -0.34255636
			},
			{
				"m_X": -1.4202543,
				"m_Y": -0.37542745
			},
			{
				"m_X": -1.4421685,
				"m_Y": -0.40829855
			},
			{
				"m_X": -1.4421685,
				"m_Y": -0.43021262
			},
			{
				"m_X": -1.4640825,
				"m_Y": -0.47404075
			},
			{
				"m_X": -1.4640825,
				"m_Y": -0.572654
			},
			{
				"m_X": -1.4859966,
				"m_Y": -0.60552514
			},
			{
				"m_X": -1.4859966,
				"m_Y": -0.67126733
			},
			{
				"m_X": -1.4969536,
				"m_Y": -0.68222433
			},
			{
				"m_X": -1.4969536,
				"m_Y": -0.7479665
			},
			{
				"m_X": -1.5079106,
				"m_Y": -0.7589236
			},
			{
				"m_X": -1.5079106,
				"m_Y": -0.86849385
			},
			{
				"m_X": -1.5298247,
				"m_Y": -0.912322
			},
			{
				"m_X": -1.5298247,
				"m_Y": -0.9671072
			},
			{
				"m_X": -1.5407817,
				"m_Y": -0.9780642
			},
			{
				"m_X": -1.5407817,
				"m_Y": -0.99997824
			},
			{
				"m_X": -1.5626957,
				"m_Y": -1.0438064
			},
			{
				"m_X": -1.5626957,
				"m_Y": -1.0766774
			},
			{
				"m_X": -1.5846099,
				"m_Y": -1.0985916
			},
			{
				"m_X": -1.5955669,
				"m_Y": -1.0985916
			},
			{
				"m_X": -1.628438,
				"m_Y": -1.1314627
			},
			{
				"m_X": -1.639395,
				"m_Y": -1.1205056
			}
		],
		[
			{
				"m_X": 1.9764254,
				"m_Y": -0.30968526
			},
			{
				"m_X": 1.9764254,
				"m_Y": -0.23298605
			},
			{
				"m_X": 2.0202534,
				"m_Y": -0.18915793
			},
			{
				"m_X": 2.0202534,
				"m_Y": -0.1782009
			},
			{
				"m_X": 2.0640817,
				"m_Y": -0.12341574
			},
			{
				"m_X": 2.0640817,
				"m_Y": -0.10150167
			},
			{
				"m_X": 2.0859957,
				"m_Y": -0.05767355
			},
			{
				"m_X": 2.0859957,
				"m_Y": -0.013845424
			},
			{
				"m_X": 2.0969527,
				"m_Y": -0.0028883922
			},
			{
				"m_X": 2.0969527,
				"m_Y": 0.17242411
			},
			{
				"m_X": 2.1079097,
				"m_Y": 0.18338114
			},
			{
				"m_X": 2.1188667,
				"m_Y": 0.22720927
			},
			{
				"m_X": 2.140781,
				"m_Y": 0.24912333
			},
			{
				"m_X": 2.140781,
				"m_Y": 0.26008037
			},
			{
				"m_X": 2.173652,
				"m_Y": 0.29295146
			},
			{
				"m_X": 2.184609,
				"m_Y": 0.29295146
			},
			{
				"m_X": 2.2174802,
				"m_Y": 0.32582256
			},
			{
				"m_X": 2.2284372,
				"m_Y": 0.32582256
			},
			{
				"m_X": 2.2722652,
				"m_Y": 0.35869366
			},
			{
				"m_X": 2.3051364,
				"m_Y": 0.3696507
			},
			{
				"m_X": 2.3270504,
				"m_Y": 0.39156476
			},
			{
				"m_X": 2.3599215,
				"m_Y": 0.4134788
			},
			{
				"m_X": 2.4147067,
				"m_Y": 0.42443582
			},
			{
				"m_X": 2.4256637,
				"m_Y": 0.43539286
			},
			{
				"m_X": 2.4585347,
				"m_Y": 0.43539286
			},
			{
				"m_X": 2.4694917,
				"m_Y": 0.4463499
			},
			{
				"m_X": 2.502363,
				"m_Y": 0.4463499
			},
			{
				"m_X": 2.51332,
				"m_Y": 0.45730692
			},
			{
				"m_X": 2.7324605,
				"m_Y": 0.45730692
			},
			{
				"m_X": 2.7434175,
				"m_Y": 0.4463499
			},
			{
				"m_X": 2.8201168,
				"m_Y": 0.43539286
			},
			{
				"m_X": 2.885859,
				"m_Y": 0.39156476
			},
			{
				"m_X": 2.885859,
				"m_Y": 0.3696507
			},
			{
				"m_X": 2.874902,
				"m_Y": 0.34773663
			},
			{
				"m_X": 2.7543745,
				"m_Y": 0.34773663
			},
			{
				"m_X": 2.7434175,
				"m_Y": 0.3367796
			},
			{
				"m_X": 2.6448042,
				"m_Y": 0.32582256
			},
			{
				"m_X": 2.6338472,
				"m_Y": 0.31486553
			},
			{
				"m_X": 2.6119332,
				"m_Y": 0.31486553
			},
			{
				"m_X": 2.5790622,
				"m_Y": 0.28199443
			},
			{
				"m_X": 2.5790622,
				"m_Y": 0.24912333
			},
			{
				"m_X": 2.6119332,
				"m_Y": 0.21625224
			},
			{
				"m_X": 2.7434175,
				"m_Y": 0.21625224
			},
			{
				"m_X": 2.7982028,
				"m_Y": 0.18338114
			},
			{
				"m_X": 2.7982028,
				"m_Y": 0.17242411
			},
			{
				"m_X": 2.7872458,
				"m_Y": 0.16146708
			},
			{
				"m_X": 2.7653317,
				"m_Y": 0.16146708
			},
			{
				"m_X": 2.7543745,
				"m_Y": 0.15051004
			},
			{
				"m_X": 2.7324605,
				"m_Y": 0.15051004
			},
			{
				"m_X": 2.7215035,
				"m_Y": 0.13955301
			},
			{
				"m_X": 2.6995895,
				"m_Y": 0.13955301
			},
			{
				"m_X": 2.6886325,
				"m_Y": 0.128596
			},
			{
				"m_X": 2.6667185,
				"m_Y": 0.128596
			},
			{
				"m_X": 2.6557612,
				"m_Y": 0.11763895
			},
			{
				"m_X": 2.568105,
				"m_Y": 0.09572489
			},
			{
				"m_X": 2.535234,
				"m_Y": 0.0628538
			},
			{
				"m_X": 2.535234,
				"m_Y": 0.051896766
			},
			{
				"m_X": 2.568105,
				"m_Y": 0.01902567
			},
			{
				"m_X": 2.5900192,
				"m_Y": 0.01902567
			},
			{
				"m_X": 2.6009762,
				"m_Y": 0.008068639
			},
			{
				"m_X": 2.6448042,
				"m_Y": 0.008068639
			},
			{
				"m_X": 2.6557612,
				"m_Y": -0.0028883922
			},
			{
				"m_X": 2.6886325,
				"m_Y": -0.0028883922
			},
			{
				"m_X": 2.6995895,
				"m_Y": -0.035759486
			},
			{
				"m_X": 2.6667185,
				"m_Y": -0.079587616
			},
			{
				"m_X": 2.6557612,
				"m_Y": -0.09054464
			},
			{
				"m_X": 2.568105,
				"m_Y": -0.09054464
			},
			{
				"m_X": 2.557148,
				"m_Y": -0.10150167
			},
			{
				"m_X": 2.4694917,
				"m_Y": -0.10150167
			},
			{
				"m_X": 2.4585347,
				"m_Y": -0.112458706
			},
			{
				"m_X": 2.3927925,
				"m_Y": -0.112458706
			},
			{
				"m_X": 2.3818355,
				"m_Y": -0.12341574
			},
			{
				"m_X": 2.2941792,
				"m_Y": -0.13437277
			},
			{
				"m_X": 2.2613082,
				"m_Y": -0.16724387
			},
			{
				"m_X": 2.2613082,
				"m_Y": -0.1782009
			},
			{
				"m_X": 2.2941792,
				"m_Y": -0.211072
			},
			{
				"m_X": 2.3708785,
				"m_Y": -0.22202902
			},
			{
				"m_X": 2.3927925,
				"m_Y": -0.23298605
			},
			{
				"m_X": 2.2832222,
				"m_Y": -0.23298605
			},
			{
				"m_X": 2.2722652,
				"m_Y": -0.24394308
			},
			{
				"m_X": 2.195566,
				"m_Y": -0.24394308
			},
			{
				"m_X": 2.162695,
				"m_Y": -0.26585716
			},
			{
				"m_X": 2.140781,
				"m_Y": -0.26585716
			},
			{
				"m_X": 2.1079097,
				"m_Y": -0.28777122
			},
			{
				"m_X": 2.0859957,
				"m_Y": -0.28777122
			},
			{
				"m_X": 2.0421677,
				"m_Y": -0.3206423
			},
			{
				"m_X": 2.0092964,
				"m_Y": -0.3206423
			},
			{
				"m_X": 1.9873824,
				"m_Y": -0.33159932
			}
		],
		[
			{
				"m_X": 1.132734,
				"m_Y": -0.16724387
			},
			{
				"m_X": 1.0012496,
				"m_Y": -0.05767355
			},
			{
				"m_X": 0.99029255,
				"m_Y": 0.008068639
			},
			{
				"m_X": 0.97933555,
				"m_Y": 0.15051004
			},
			{
				"m_X": 0.99029255,
				"m_Y": 0.16146708
			},
			{
				"m_X": 1.0560347,
				"m_Y": 0.28199443
			},
			{
				"m_X": 1.1546481,
				"m_Y": 0.31486553
			},
			{
				"m_X": 1.2423043,
				"m_Y": 0.32582256
			},
			{
				"m_X": 1.4395308,
				"m_Y": 0.34773663
			},
			{
				"m_X": 1.4066597,
				"m_Y": 0.3039085
			},
			{
				"m_X": 1.4066597,
				"m_Y": 0.22720927
			},
			{
				"m_X": 1.494316,
				"m_Y": 0.16146708
			},
			{
				"m_X": 1.6477145,
				"m_Y": 0.15051004
			},
			{
				"m_X": 1.7024996,
				"m_Y": 0.0628538
			},
			{
				"m_X": 1.7134566,
				"m_Y": 0.008068639
			},
			{
				"m_X": 1.7244136,
				"m_Y": -0.05767355
			},
			{
				"m_X": 1.7353706,
				"m_Y": -0.13437277
			},
			{
				"m_X": 1.7024996,
				"m_Y": -0.1453298
			},
			{
				"m_X": 1.5600582,
				"m_Y": -0.16724387
			},
			{
				"m_X": 1.483359,
				"m_Y": -0.18915793
			},
			{
				"m_X": 1.2970895,
				"m_Y": -0.20011497
			},
			{
				"m_X": 1.2861325,
				"m_Y": -0.18915793
			}
		],
		[
			{
				"m_X": -0.29168013,
				"m_Y": 0.0628538
			},
			{
				"m_X": -0.32455122,
				"m_Y": 0.09572489
			},
			{
				"m_X": -0.39029342,
				"m_Y": 0.10668192
			},
			{
				"m_X": -0.40125045,
				"m_Y": 0.11763895
			},
			{
				"m_X": -0.42316452,
				"m_Y": 0.11763895
			},
			{
				"m_X": -0.46699265,
				"m_Y": 0.13955301
			},
			{
				"m_X": -0.49986374,
				"m_Y": 0.13955301
			},
			{
				"m_X": -0.5546489,
				"m_Y": 0.17242411
			},
			{
				"m_X": -0.5546489,
				"m_Y": 0.19433817
			},
			{
				"m_X": -0.51082075,
				"m_Y": 0.2052952
			},
			{
				"m_X": -0.49986374,
				"m_Y": 0.21625224
			},
			{
				"m_X": -0.3793364,
				"m_Y": 0.21625224
			},
			{
				"m_X": -0.33550826,
				"m_Y": 0.26008037
			},
			{
				"m_X": -0.33550826,
				"m_Y": 0.28199443
			},
			{
				"m_X": -0.36837935,
				"m_Y": 0.31486553
			},
			{
				"m_X": -0.41220748,
				"m_Y": 0.31486553
			},
			{
				"m_X": -0.42316452,
				"m_Y": 0.32582256
			},
			{
				"m_X": -0.51082075,
				"m_Y": 0.3367796
			},
			{
				"m_X": -0.5217778,
				"m_Y": 0.34773663
			},
			{
				"m_X": -0.63134813,
				"m_Y": 0.34773663
			},
			{
				"m_X": -0.64230514,
				"m_Y": 0.39156476
			},
			{
				"m_X": -0.57656294,
				"m_Y": 0.43539286
			},
			{
				"m_X": -0.5546489,
				"m_Y": 0.43539286
			},
			{
				"m_X": -0.5436919,
				"m_Y": 0.4463499
			},
			{
				"m_X": -0.49986374,
				"m_Y": 0.4463499
			},
			{
				"m_X": -0.4889067,
				"m_Y": 0.45730692
			},
			{
				"m_X": -0.2807231,
				"m_Y": 0.45730692
			},
			{
				"m_X": -0.26976606,
				"m_Y": 0.4463499
			},
			{
				"m_X": -0.22593795,
				"m_Y": 0.4463499
			},
			{
				"m_X": -0.18210982,
				"m_Y": 0.42443582
			},
			{
				"m_X": -0.14923874,
				"m_Y": 0.42443582
			},
			{
				"m_X": -0.050625443,
				"m_Y": 0.3696507
			},
			{
				"m_X": 0.08085893,
				"m_Y": 0.28199443
			},
			{
				"m_X": 0.08085893,
				"m_Y": 0.2710374
			},
			{
				"m_X": 0.12468706,
				"m_Y": 0.21625224
			},
			{
				"m_X": 0.12468706,
				"m_Y": 0.19433817
			},
			{
				"m_X": 0.15755816,
				"m_Y": 0.128596
			},
			{
				"m_X": 0.15755816,
				"m_Y": 0.10668192
			},
			{
				"m_X": 0.16851519,
				"m_Y": 0.09572489
			},
			{
				"m_X": 0.17947222,
				"m_Y": 0.051896766
			},
			{
				"m_X": -0.30263716,
				"m_Y": 0.040939733
			},
			{
				"m_X": -0.29168013,
				"m_Y": 0.051896766
			}
		]
	],
	"m_Pivot": {
		"m_X": 0.43200555,
		"m_Y": 0.6962465
	},
	"m_PixelsToUnits": 91.265594,
	"m_PrefabAsset": { "m_Collection": "sharedassets2.assets", "m_PathID": 0 },
	"m_PrefabInstance": { "m_Collection": "sharedassets2.assets", "m_PathID": 0 },
	"m_RD": {
		"m_AlphaTexture": { "m_Collection": "sharedassets2.assets", "m_PathID": 0 },
		"m_AtlasRectOffset": {
			"m_X": -1,
			"m_Y": -1
		},
		"m_Bindpose": [
			
		],
		"m_DownscaleMultiplier": 1,
		"m_IndexBuffer": "FQAWABcAEgAUABUAEgATABQADwARABIADwASAAoADwAQABEACQAGAAcADQAOAA8ADwALAAwADAANAA8ADwAKAAsAEgAJAAoAEgAVAAkACQAVAAYACQAHAAgAAQAGABUAAQAFAAYAAgADAAQAAgAEAAUAAQACAAUAAAABABUAAAAVABcA",
		"m_SecondaryTextures": [
			
		],
		"m_SettingsRaw": 64,
		"m_SubMeshes": [
			{
				"m_BaseVertex": 0,
				"m_FirstByte": 0,
				"m_FirstVertex": 0,
				"m_IndexCount": 66,
				"m_LocalAABB": {
					"m_Center": {
						"m_X": 0,
						"m_Y": 0,
						"m_Z": 0
					},
					"m_Extent": {
						"m_X": 0,
						"m_Y": 0,
						"m_Z": 0
					}
				},
				"m_Topology": 0,
				"m_VertexCount": 24
			}
		],
		"m_Texture": { "m_Collection": "sharedassets2.assets", "m_PathID": 89 },
		"m_TextureRect": {
			"m_Height": 274.84778,
			"m_Width": 505.91418,
			"m_X": 1534.6543,
			"m_Y": 280.58374
		},
		"m_TextureRectOffset": {
			"m_X": 0,
			"m_Y": 0
		},
		"m_UvTransform": {
			"m_W": 471.94556,
			"m_X": 91.265594,
			"m_Y": 1753.212,
			"m_Z": 91.265594
		},
		"m_VertexData": {
			"m_Channels": [
				{
					"m_Dimension": 3,
					"m_Format": 0,
					"m_Offset": 0,
					"m_Stream": 0
				},
				{
					"m_Dimension": 0,
					"m_Format": 0,
					"m_Offset": 0,
					"m_Stream": 0
				},
				{
					"m_Dimension": 0,
					"m_Format": 0,
					"m_Offset": 0,
					"m_Stream": 0
				},
				{
					"m_Dimension": 0,
					"m_Format": 0,
					"m_Offset": 0,
					"m_Stream": 0
				},
				{
					"m_Dimension": 2,
					"m_Format": 0,
					"m_Offset": 0,
					"m_Stream": 1
				},
				{
					"m_Dimension": 0,
					"m_Format": 0,
					"m_Offset": 0,
					"m_Stream": 0
				},
				{
					"m_Dimension": 0,
					"m_Format": 0,
					"m_Offset": 0,
					"m_Stream": 0
				},
				{
					"m_Dimension": 0,
					"m_Format": 0,
					"m_Offset": 0,
					"m_Stream": 0
				},
				{
					"m_Dimension": 0,
					"m_Format": 0,
					"m_Offset": 0,
					"m_Stream": 0
				},
				{
					"m_Dimension": 0,
					"m_Format": 0,
					"m_Offset": 0,
					"m_Stream": 0
				},
				{
					"m_Dimension": 0,
					"m_Format": 0,
					"m_Offset": 0,
					"m_Stream": 0
				},
				{
					"m_Dimension": 0,
					"m_Format": 0,
					"m_Offset": 0,
					"m_Stream": 0
				},
				{
					"m_Dimension": 0,
					"m_Format": 0,
					"m_Offset": 0,
					"m_Stream": 0
				},
				{
					"m_Dimension": 0,
					"m_Format": 0,
					"m_Offset": 0,
					"m_Stream": 0
				}
			],
			"m_Data": "ZmbGPyUfSj8AAAAAKFzvP6+k+j4AAAAAFK4nQFZSPT8AAAAA9yhMQMePBz8AAAAAo3A9QOi7Jb0AAAAAFK4nQPPLwr4AAAAAZmYGQEweAL8AAAAAxPXoP4Oe4r8AAAAAzMwMP0FPAcAAAAAArkfhPfLbzL8AAAAA9igcv53eA8AAAAAArkeBv39ZCMAAAAAAXI/iv5ZM6r8AAAAAuR4FwDDm478AAAAAzcwcwKEjjr8AAAAASOH6v7OEZr8AAAAA16Pwv6uNLr4AAAAAuB7Fv2rayz0AAAAACtdjv4KlBD4AAAAAxPVovxpIJj8AAAAAth6FvukUMz8AAAAAp3C9PhFxAj8AAAAAWo8CP6gKXD8AAAAA16OQPzH2bT8AAAAAAAAAAAAAAAAAAAAAAAAAAAAAAAAAAAAAAAAAAAAAAAAAAAAAAAAAAAAAAAAAAAAAAAAAAAAAAAAAAAAAAAAAAAAAAAAAAAAAAAAAAAAAAAAAAAAAAAAAAAAAAAAAAAAAAAAAAAAAAAAAAAAAAAAAAAAAAAAAAAAAAAAAAAAAAAAAAAAAAAAAAAAAAAAAAAAAAAAAAAAAAAAAAAAAAAAAAAAAAAAAAAAAAAAAAAAAAAAAAAAAAAAAAAAAAAAAAAAA",
			"m_VertexCount": 24
		}
	},
	"m_Rect": {
		"m_Height": 274.84778,
		"m_Width": 505.91418,
		"m_X": 1534.6543,
		"m_Y": 280.58374
	},
	"m_RenderDataKey": {
		"Key": {
			"m_Data_0_": 211064777,
			"m_Data_1_": 1236661936,
			"m_Data_2_": 1604620988,
			"m_Data_3_": 1263556805
		},
		"Value": 8248461327151817147
	},
	"m_SpriteAtlas": { "m_Collection": "sharedassets2.assets", "m_PathID": 0 },
	"m_SpriteID": ""
}