{
	"m_AtlasName": "",
	"m_AtlasRD": {
		"m_AlphaTexture": { "m_Collection": "cab-3c0b6d0158b163c9df24e66fb67aff1a", "m_PathID": 0 },
		"m_AtlasRectOffset": {
			"m_X": 0,
			"m_Y": 0
		},
		"m_Bindpose": [
			
		],
		"m_DownscaleMultiplier": 0,
		"m_IndexBuffer": "",
		"m_SecondaryTextures": [
			
		],
		"m_SettingsRaw": 0,
		"m_SubMeshes": [
			
		],
		"m_Texture": { "m_Collection": "cab-3c0b6d0158b163c9df24e66fb67aff1a", "m_PathID": 0 },
		"m_TextureRect": {
			"m_Height": 0,
			"m_Width": 0,
			"m_X": 0,
			"m_Y": 0
		},
		"m_TextureRectOffset": {
			"m_X": 0,
			"m_Y": 0
		},
		"m_UvTransform": {
			"m_W": 0,
			"m_X": 0,
			"m_Y": 0,
			"m_Z": 0
		},
		"m_VertexData": {
			"m_Channels": [
				
			],
			"m_Data": "",
			"m_VertexCount": 0
		}
	},
	"m_AtlasTags": [
		
	],
	"m_Bones": [
		
	],
	"m_Border": {
		"m_W": 0,
		"m_X": 0,
		"m_Y": 0,
		"m_Z": 0
	},
	"m_CorrespondingSourceObject": { "m_Collection": "cab-3c0b6d0158b163c9df24e66fb67aff1a", "m_PathID": 0 },
	"m_Extrude": 1,
	"m_HideFlags": 0,
	"m_IsPolygon": false,
	"m_Name": "HW2021Witch_killGun_imposter0002",
	"m_Offset": {
		"m_X": 256.52145,
		"m_Y": 61.00645
	},
	"m_PackingTag": "",
	"m_PhysicsShape": [
		[
			{
				"m_X": -3.25,
				"m_Y": -1.0699999
			},
			{
				"m_X": -3.27,
				"m_Y": -1.17
			},
			{
				"m_X": -3.27,
				"m_Y": -1.3299999
			},
			{
				"m_X": -3.05,
				"m_Y": -1.3299999
			},
			{
				"m_X": -3.05,
				"m_Y": -1.3199999
			},
			{
				"m_X": -3.1799998,
				"m_Y": -1.09
			},
			{
				"m_X": -3.21,
				"m_Y": -1.06
			}
		],
		[
			{
				"m_X": -1.9599999,
				"m_Y": -1.14
			},
			{
				"m_X": -2.07,
				"m_Y": -1.3199999
			},
			{
				"m_X": -2.07,
				"m_Y": -1.3299999
			},
			{
				"m_X": -1.91,
				"m_Y": -1.3299999
			},
			{
				"m_X": -1.91,
				"m_Y": -1.16
			},
			{
				"m_X": -1.93,
				"m_Y": -1.14
			}
		],
		[
			{
				"m_X": -1.9799999,
				"m_Y": -1.03
			},
			{
				"m_X": -1.93,
				"m_Y": -0.84999996
			},
			{
				"m_X": -1.86,
				"m_Y": -0.89
			},
			{
				"m_X": -1.81,
				"m_Y": -0.78999996
			},
			{
				"m_X": -1.6999999,
				"m_Y": -0.83
			},
			{
				"m_X": -1.65,
				"m_Y": -0.81
			},
			{
				"m_X": -1.65,
				"m_Y": -0.69
			},
			{
				"m_X": -1.81,
				"m_Y": -0.38
			},
			{
				"m_X": -1.6899999,
				"m_Y": -0.02
			},
			{
				"m_X": -1.67,
				"m_Y": 0.07
			},
			{
				"m_X": -1.6899999,
				"m_Y": 0.089999996
			},
			{
				"m_X": -1.7199999,
				"m_Y": 0.08
			},
			{
				"m_X": -1.87,
				"m_Y": -0.099999994
			},
			{
				"m_X": -2.06,
				"m_Y": -0.21
			},
			{
				"m_X": -2.24,
				"m_Y": -0.34
			},
			{
				"m_X": -2.3799999,
				"m_Y": -0.22
			},
			{
				"m_X": -2.6,
				"m_Y": -0.13
			},
			{
				"m_X": -2.74,
				"m_Y": -0.11
			},
			{
				"m_X": -3.02,
				"m_Y": -0.099999994
			},
			{
				"m_X": -3.28,
				"m_Y": 0.06
			},
			{
				"m_X": -3.32,
				"m_Y": 0.06
			},
			{
				"m_X": -3.35,
				"m_Y": 0.049999997
			},
			{
				"m_X": -3.32,
				"m_Y": -0.049999997
			},
			{
				"m_X": -3.1399999,
				"m_Y": -0.38
			},
			{
				"m_X": -3.21,
				"m_Y": -0.39999998
			},
			{
				"m_X": -3.32,
				"m_Y": -0.48
			},
			{
				"m_X": -3.4099998,
				"m_Y": -0.65
			},
			{
				"m_X": -3.4199998,
				"m_Y": -0.71999997
			},
			{
				"m_X": -3.4199998,
				"m_Y": -0.89
			},
			{
				"m_X": -3.3899999,
				"m_Y": -0.9
			},
			{
				"m_X": -3.1799998,
				"m_Y": -0.78999996
			},
			{
				"m_X": -3.1,
				"m_Y": -0.84999996
			},
			{
				"m_X": -3.07,
				"m_Y": -1.13
			},
			{
				"m_X": -2.95,
				"m_Y": -1.2099999
			},
			{
				"m_X": -2.78,
				"m_Y": -1.31
			},
			{
				"m_X": -2.72,
				"m_Y": -1.31
			},
			{
				"m_X": -2.6,
				"m_Y": -1.2099999
			},
			{
				"m_X": -2.5,
				"m_Y": -1.1
			},
			{
				"m_X": -2.24,
				"m_Y": -1.22
			},
			{
				"m_X": -2.21,
				"m_Y": -1.22
			}
		],
		[
			{
				"m_X": -3.49,
				"m_Y": -1.02
			},
			{
				"m_X": -3.49,
				"m_Y": -1.15
			},
			{
				"m_X": -3.46,
				"m_Y": -1.14
			},
			{
				"m_X": -3.4499998,
				"m_Y": -1.09
			},
			{
				"m_X": -3.4399998,
				"m_Y": -1.02
			},
			{
				"m_X": -3.47,
				"m_Y": -1
			}
		],
		[
			{
				"m_X": -3.49,
				"m_Y": 0.01
			},
			{
				"m_X": -3.49,
				"m_Y": -0.08
			},
			{
				"m_X": -3.46,
				"m_Y": -0.07
			},
			{
				"m_X": -3.4399998,
				"m_Y": 0.01
			},
			{
				"m_X": -3.47,
				"m_Y": 0.03
			}
		]
	],
	"m_Pivot": {
		"m_X": 1.8869241,
		"m_Y": 0.9236939
	},
	"m_PixelsToUnits": 100,
	"m_PrefabAsset": { "m_Collection": "cab-3c0b6d0158b163c9df24e66fb67aff1a", "m_PathID": 0 },
	"m_PrefabInstance": { "m_Collection": "cab-3c0b6d0158b163c9df24e66fb67aff1a", "m_PathID": 0 },
	"m_RD": {
		"m_AlphaTexture": { "m_Collection": "cab-3c0b6d0158b163c9df24e66fb67aff1a", "m_PathID": 0 },
		"m_AtlasRectOffset": {
			"m_X": -1,
			"m_Y": -1
		},
		"m_Bindpose": [
			
		],
		"m_DownscaleMultiplier": 1,
		"m_IndexBuffer": "BwAIAAkABQAHAAkABQAGAAcAAgAFAAkAAAAJAAoABAACAAMAAgAEAAUAAQACAAkAAAABAAkA",
		"m_SecondaryTextures": [
			
		],
		"m_SettingsRaw": 64,
		"m_SubMeshes": [
			{
				"m_BaseVertex": 0,
				"m_FirstByte": 0,
				"m_FirstVertex": 0,
				"m_IndexCount": 27,
				"m_LocalAABB": {
					"m_Center": {
						"m_X": 0,
						"m_Y": 0,
						"m_Z": 0
					},
					"m_Extent": {
						"m_X": 0,
						"m_Y": 0,
						"m_Z": 0
					}
				},
				"m_Topology": 0,
				"m_VertexCount": 11
			}
		],
		"m_Texture": { "m_Collection": "cab-3c0b6d0158b163c9df24e66fb67aff1a", "m_PathID": 516243593469798276 },
		"m_TextureRect": {
			"m_Height": 143.98709,
			"m_Width": 184.95709,
			"m_X": 1814,
			"m_Y": 1901
		},
		"m_TextureRectOffset": {
			"m_X": 0,
			"m_Y": 0
		},
		"m_UvTransform": {
			"m_W": 2034,
			"m_X": 100,
			"m_Y": 2163,
			"m_Z": 100
		},
		"m_VertexData": {
			"m_Channels": [
				{
					"m_Dimension": 3,
					"m_Format": 0,
					"m_Offset": 0,
					"m_Stream": 0
				},
				{
					"m_Dimension": 0,
					"m_Format": 0,
					"m_Offset": 0,
					"m_Stream": 0
				},
				{
					"m_Dimension": 0,
					"m_Format": 0,
					"m_Offset": 0,
					"m_Stream": 0
				},
				{
					"m_Dimension": 0,
					"m_Format": 0,
					"m_Offset": 0,
					"m_Stream": 0
				},
				{
					"m_Dimension": 2,
					"m_Format": 0,
					"m_Offset": 0,
					"m_Stream": 1
				},
				{
					"m_Dimension": 0,
					"m_Format": 0,
					"m_Offset": 0,
					"m_Stream": 0
				},
				{
					"m_Dimension": 0,
					"m_Format": 0,
					"m_Offset": 0,
					"m_Stream": 0
				},
				{
					"m_Dimension": 0,
					"m_Format": 0,
					"m_Offset": 0,
					"m_Stream": 0
				},
				{
					"m_Dimension": 0,
					"m_Format": 0,
					"m_Offset": 0,
					"m_Stream": 0
				},
				{
					"m_Dimension": 0,
					"m_Format": 0,
					"m_Offset": 0,
					"m_Stream": 0
				},
				{
					"m_Dimension": 0,
					"m_Format": 0,
					"m_Offset": 0,
					"m_Stream": 0
				},
				{
					"m_Dimension": 0,
					"m_Format": 0,
					"m_Offset": 0,
					"m_Stream": 0
				},
				{
					"m_Dimension": 0,
					"m_Format": 0,
					"m_Offset": 0,
					"m_Stream": 0
				},
				{
					"m_Dimension": 0,
					"m_Format": 0,
					"m_Offset": 0,
					"m_Stream": 0
				}
			],
			"m_Data": "hevRv+F6VL8AAAAAexQOwFK4nr8AAAAAMzMjwDMzk78AAAAAKVwvwHA9qr8AAAAAMzNDwDMzk78AAAAAKVxPwML1aL8AAAAAKVxfwB6Fa78AAAAA16NQwJmZGb4AAAAA61FYwOtRuD0AAAAAwvUIwAAAgL4AAAAAj8LVv7geBT4AAAAAAAAAAAAAAAAAAAAAAAAAAAAAAAAAAAAAAAAAAAAAAAAAAAAAAAAAAAAAAAAAAAAAAAAAAAAAAAAAAAAAAAAAAAAAAAAAAAAAAAAAAAAAAAAAAAAAAAAAAAAAAAAAAAAAAAAAAA==",
			"m_VertexCount": 11
		}
	},
	"m_Rect": {
		"m_Height": 143.98709,
		"m_Width": 184.95709,
		"m_X": 1814,
		"m_Y": 1901
	},
	"m_RenderDataKey": {
		"Key": {
			"m_Data_0_": 4030047445,
			"m_Data_1_": 1209261837,
			"m_Data_2_": 2774680221,
			"m_Data_3_": 2719022564
		},
		"Value": -1510332365481227533
	},
	"m_SpriteAtlas": { "m_Collection": "cab-3c0b6d0158b163c9df24e66fb67aff1a", "m_PathID": 0 },
	"m_SpriteID": ""
}