{
	"m_AtlasName": "",
	"m_AtlasRD": {
		"m_AlphaTexture": { "m_Collection": "cab-3c0b6d0158b163c9df24e66fb67aff1a", "m_PathID": 0 },
		"m_AtlasRectOffset": {
			"m_X": 0,
			"m_Y": 0
		},
		"m_Bindpose": [
			
		],
		"m_DownscaleMultiplier": 0,
		"m_IndexBuffer": "",
		"m_SecondaryTextures": [
			
		],
		"m_SettingsRaw": 0,
		"m_SubMeshes": [
			
		],
		"m_Texture": { "m_Collection": "cab-3c0b6d0158b163c9df24e66fb67aff1a", "m_PathID": 0 },
		"m_TextureRect": {
			"m_Height": 0,
			"m_Width": 0,
			"m_X": 0,
			"m_Y": 0
		},
		"m_TextureRectOffset": {
			"m_X": 0,
			"m_Y": 0
		},
		"m_UvTransform": {
			"m_W": 0,
			"m_X": 0,
			"m_Y": 0,
			"m_Z": 0
		},
		"m_VertexData": {
			"m_Channels": [
				
			],
			"m_Data": "",
			"m_VertexCount": 0
		}
	},
	"m_AtlasTags": [
		
	],
	"m_Bones": [
		
	],
	"m_Border": {
		"m_W": 0,
		"m_X": 0,
		"m_Y": 0,
		"m_Z": 0
	},
	"m_CorrespondingSourceObject": { "m_Collection": "cab-3c0b6d0158b163c9df24e66fb67aff1a", "m_PathID": 0 },
	"m_Extrude": 1,
	"m_HideFlags": 0,
	"m_IsPolygon": false,
	"m_Name": "Scientist_killGun_imposter0008",
	"m_Offset": {
		"m_X": 263.5,
		"m_Y": 71.99999
	},
	"m_PackingTag": "",
	"m_PhysicsShape": [
		[
			{
				"m_X": -2.61,
				"m_Y": -1.36
			},
			{
				"m_X": -2.61,
				"m_Y": -1.38
			},
			{
				"m_X": -2.07,
				"m_Y": -1.38
			},
			{
				"m_X": -2.08,
				"m_Y": -1.35
			},
			{
				"m_X": -2.44,
				"m_Y": -1.17
			},
			{
				"m_X": -2.53,
				"m_Y": -1.17
			},
			{
				"m_X": -2.56,
				"m_Y": -1.18
			}
		],
		[
			{
				"m_X": -2.3799999,
				"m_Y": -0.96
			},
			{
				"m_X": -2.11,
				"m_Y": -1.04
			},
			{
				"m_X": -2.06,
				"m_Y": -1.15
			},
			{
				"m_X": -2,
				"m_Y": -1.1899999
			},
			{
				"m_X": -1.73,
				"m_Y": -1.1899999
			},
			{
				"m_X": -1.63,
				"m_Y": -1.14
			},
			{
				"m_X": -1.63,
				"m_Y": -0.89
			},
			{
				"m_X": -1.64,
				"m_Y": -0.79999995
			},
			{
				"m_X": -1.7099999,
				"m_Y": -0.7
			},
			{
				"m_X": -1.63,
				"m_Y": -0.47
			},
			{
				"m_X": -1.63,
				"m_Y": -0.28
			},
			{
				"m_X": -2.02,
				"m_Y": -0.32999998
			},
			{
				"m_X": -2.06,
				"m_Y": -0.29999998
			},
			{
				"m_X": -2.51,
				"m_Y": -0.21
			},
			{
				"m_X": -2.71,
				"m_Y": -0.099999994
			},
			{
				"m_X": -2.81,
				"m_Y": -0.099999994
			},
			{
				"m_X": -2.86,
				"m_Y": -0.17
			},
			{
				"m_X": -3.07,
				"m_Y": -0.56
			},
			{
				"m_X": -3.28,
				"m_Y": -0.75
			},
			{
				"m_X": -3.4099998,
				"m_Y": -0.93
			},
			{
				"m_X": -3.4499998,
				"m_Y": -1.03
			},
			{
				"m_X": -3.4499998,
				"m_Y": -1.1899999
			},
			{
				"m_X": -3.37,
				"m_Y": -1.3
			},
			{
				"m_X": -3.32,
				"m_Y": -1.3199999
			},
			{
				"m_X": -3.09,
				"m_Y": -1.3199999
			},
			{
				"m_X": -2.71,
				"m_Y": -1.1999999
			},
			{
				"m_X": -2.62,
				"m_Y": -1.14
			},
			{
				"m_X": -2.53,
				"m_Y": -1.05
			}
		],
		[
			{
				"m_X": -3.01,
				"m_Y": -0.089999996
			},
			{
				"m_X": -3.06,
				"m_Y": -0.06
			},
			{
				"m_X": -3.6399999,
				"m_Y": -0.06
			},
			{
				"m_X": -3.6399999,
				"m_Y": -0.94
			},
			{
				"m_X": -3.52,
				"m_Y": -0.94
			},
			{
				"m_X": -3.32,
				"m_Y": -0.78999996
			},
			{
				"m_X": -3.01,
				"m_Y": -0.39
			}
		],
		[
			{
				"m_X": -2.1299999,
				"m_Y": -0.06
			},
			{
				"m_X": -2.1299999,
				"m_Y": -0.12
			},
			{
				"m_X": -2.05,
				"m_Y": -0.17999999
			},
			{
				"m_X": -1.8,
				"m_Y": -0.17999999
			},
			{
				"m_X": -1.7199999,
				"m_Y": -0.14999999
			},
			{
				"m_X": -1.66,
				"m_Y": -0.099999994
			},
			{
				"m_X": -1.65,
				"m_Y": -0.06
			}
		]
	],
	"m_Pivot": {
		"m_X": 1.8109453,
		"m_Y": 1.0454545
	},
	"m_PixelsToUnits": 100,
	"m_PrefabAsset": { "m_Collection": "cab-3c0b6d0158b163c9df24e66fb67aff1a", "m_PathID": 0 },
	"m_PrefabInstance": { "m_Collection": "cab-3c0b6d0158b163c9df24e66fb67aff1a", "m_PathID": 0 },
	"m_RD": {
		"m_AlphaTexture": { "m_Collection": "cab-3c0b6d0158b163c9df24e66fb67aff1a", "m_PathID": 0 },
		"m_AtlasRectOffset": {
			"m_X": -1,
			"m_Y": -1
		},
		"m_Bindpose": [
			
		],
		"m_DownscaleMultiplier": 1,
		"m_IndexBuffer": "BQAGAAcAAAAEAAUAAgADAAQABAAAAAEABAABAAIAAAAFAAcA",
		"m_SecondaryTextures": [
			
		],
		"m_SettingsRaw": 64,
		"m_SubMeshes": [
			{
				"m_BaseVertex": 0,
				"m_FirstByte": 0,
				"m_FirstVertex": 0,
				"m_IndexCount": 18,
				"m_LocalAABB": {
					"m_Center": {
						"m_X": 0,
						"m_Y": 0,
						"m_Z": 0
					},
					"m_Extent": {
						"m_X": 0,
						"m_Y": 0,
						"m_Z": 0
					}
				},
				"m_Topology": 0,
				"m_VertexCount": 8
			}
		],
		"m_Texture": { "m_Collection": "cab-3c0b6d0158b163c9df24e66fb67aff1a", "m_PathID": 7340132284488021289 },
		"m_TextureRect": {
			"m_Height": 132,
			"m_Width": 201,
			"m_X": 135,
			"m_Y": 1481
		},
		"m_TextureRectOffset": {
			"m_X": 0,
			"m_Y": 0
		},
		"m_UvTransform": {
			"m_W": 1619,
			"m_X": 100,
			"m_Y": 499,
			"m_Z": 100
		},
		"m_VertexData": {
			"m_Channels": [
				{
					"m_Dimension": 3,
					"m_Format": 0,
					"m_Offset": 0,
					"m_Stream": 0
				},
				{
					"m_Dimension": 0,
					"m_Format": 0,
					"m_Offset": 0,
					"m_Stream": 0
				},
				{
					"m_Dimension": 0,
					"m_Format": 0,
					"m_Offset": 0,
					"m_Stream": 0
				},
				{
					"m_Dimension": 0,
					"m_Format": 0,
					"m_Offset": 0,
					"m_Stream": 0
				},
				{
					"m_Dimension": 2,
					"m_Format": 0,
					"m_Offset": 0,
					"m_Stream": 1
				},
				{
					"m_Dimension": 0,
					"m_Format": 0,
					"m_Offset": 0,
					"m_Stream": 0
				},
				{
					"m_Dimension": 0,
					"m_Format": 0,
					"m_Offset": 0,
					"m_Stream": 0
				},
				{
					"m_Dimension": 0,
					"m_Format": 0,
					"m_Offset": 0,
					"m_Stream": 0
				},
				{
					"m_Dimension": 0,
					"m_Format": 0,
					"m_Offset": 0,
					"m_Stream": 0
				},
				{
					"m_Dimension": 0,
					"m_Format": 0,
					"m_Offset": 0,
					"m_Stream": 0
				},
				{
					"m_Dimension": 0,
					"m_Format": 0,
					"m_Offset": 0,
					"m_Stream": 0
				},
				{
					"m_Dimension": 0,
					"m_Format": 0,
					"m_Offset": 0,
					"m_Stream": 0
				},
				{
					"m_Dimension": 0,
					"m_Format": 0,
					"m_Offset": 0,
					"m_Stream": 0
				},
				{
					"m_Dimension": 0,
					"m_Format": 0,
					"m_Offset": 0,
					"m_Stream": 0
				}
			],
			"m_Data": "16MgwK5HYb4AAAAA16PQv5mZmb4AAAAA16PQvzMzk78AAAAA61H4v65Hob8AAAAAuB4VwAAAgL8AAAAAj8JFwNejsL8AAAAAwvVowK5Hob8AAAAAXI8ywI/Cdb0AAAAAAAAAAAAAAAAAAAAAAAAAAAAAAAAAAAAAAAAAAAAAAAAAAAAAAAAAAAAAAAAAAAAAAAAAAAAAAAAAAAAAAAAAAA==",
			"m_VertexCount": 8
		}
	},
	"m_Rect": {
		"m_Height": 132,
		"m_Width": 201,
		"m_X": 135,
		"m_Y": 1481
	},
	"m_RenderDataKey": {
		"Key": {
			"m_Data_0_": 257969214,
			"m_Data_1_": 1199685327,
			"m_Data_2_": 2537726869,
			"m_Data_3_": 1994929861
		},
		"Value": 72170529412579102
	},
	"m_SpriteAtlas": { "m_Collection": "cab-3c0b6d0158b163c9df24e66fb67aff1a", "m_PathID": 0 },
	"m_SpriteID": ""
}