{
	"m_AtlasName": "",
	"m_AtlasRD": {
		"m_AlphaTexture": { "m_Collection": "cab-a1828797179c75fbf9033d39ad174438", "m_PathID": 0 },
		"m_AtlasRectOffset": {
			"m_X": 0,
			"m_Y": 0
		},
		"m_Bindpose": [
			
		],
		"m_DownscaleMultiplier": 0,
		"m_IndexBuffer": "",
		"m_SecondaryTextures": [
			
		],
		"m_SettingsRaw": 0,
		"m_SubMeshes": [
			
		],
		"m_Texture": { "m_Collection": "cab-a1828797179c75fbf9033d39ad174438", "m_PathID": 0 },
		"m_TextureRect": {
			"m_Height": 0,
			"m_Width": 0,
			"m_X": 0,
			"m_Y": 0
		},
		"m_TextureRectOffset": {
			"m_X": 0,
			"m_Y": 0
		},
		"m_UvTransform": {
			"m_W": 0,
			"m_X": 0,
			"m_Y": 0,
			"m_Z": 0
		},
		"m_VertexData": {
			"m_Channels": [
				
			],
			"m_Data": "",
			"m_VertexCount": 0
		}
	},
	"m_AtlasTags": [
		
	],
	"m_Bones": [
		
	],
	"m_Border": {
		"m_W": 0,
		"m_X": 0,
		"m_Y": 0,
		"m_Z": 0
	},
	"m_CorrespondingSourceObject": { "m_Collection": "cab-a1828797179c75fbf9033d39ad174438", "m_PathID": 0 },
	"m_Extrude": 1,
	"m_HideFlags": 0,
	"m_IsPolygon": false,
	"m_Name": "tree_slider",
	"m_Offset": {
		"m_X": 1.9999994,
		"m_Y": -1.9999993
	},
	"m_PackingTag": "",
	"m_PhysicsShape": [
		[
			{
				"m_X": -0.505,
				"m_Y": -0.185
			},
			{
				"m_X": -0.49499997,
				"m_Y": -0.205
			},
			{
				"m_X": 0.465,
				"m_Y": -0.205
			},
			{
				"m_X": 0.465,
				"m_Y": 0.255
			},
			{
				"m_X": -0.475,
				"m_Y": 0.255
			},
			{
				"m_X": -0.505,
				"m_Y": 0.225
			}
		]
	],
	"m_Pivot": {
		"m_X": 0.519802,
		"m_Y": 0.4661017
	},
	"m_PixelsToUnits": 100,
	"m_PrefabAsset": { "m_Collection": "cab-a1828797179c75fbf9033d39ad174438", "m_PathID": 0 },
	"m_PrefabInstance": { "m_Collection": "cab-a1828797179c75fbf9033d39ad174438", "m_PathID": 0 },
	"m_RD": {
		"m_AlphaTexture": { "m_Collection": "cab-a1828797179c75fbf9033d39ad174438", "m_PathID": 0 },
		"m_AtlasRectOffset": {
			"m_X": -1,
			"m_Y": -1
		},
		"m_Bindpose": [
			
		],
		"m_DownscaleMultiplier": 1,
		"m_IndexBuffer": "AQACAAMAAAABAAMA",
		"m_SecondaryTextures": [
			
		],
		"m_SettingsRaw": 64,
		"m_SubMeshes": [
			{
				"m_BaseVertex": 0,
				"m_FirstByte": 0,
				"m_FirstVertex": 0,
				"m_IndexCount": 6,
				"m_LocalAABB": {
					"m_Center": {
						"m_X": 0,
						"m_Y": 0,
						"m_Z": 0
					},
					"m_Extent": {
						"m_X": 0,
						"m_Y": 0,
						"m_Z": 0
					}
				},
				"m_Topology": 0,
				"m_VertexCount": 4
			}
		],
		"m_Texture": { "m_Collection": "cab-a1828797179c75fbf9033d39ad174438", "m_PathID": 362737703605681936 },
		"m_TextureRect": {
			"m_Height": 59,
			"m_Width": 101,
			"m_X": 692,
			"m_Y": 576
		},
		"m_TextureRectOffset": {
			"m_X": 0,
			"m_Y": 0
		},
		"m_UvTransform": {
			"m_W": 603.5,
			"m_X": 100,
			"m_Y": 744.5,
			"m_Z": 100
		},
		"m_VertexData": {
			"m_Channels": [
				{
					"m_Dimension": 3,
					"m_Format": 0,
					"m_Offset": 0,
					"m_Stream": 0
				},
				{
					"m_Dimension": 0,
					"m_Format": 0,
					"m_Offset": 0,
					"m_Stream": 0
				},
				{
					"m_Dimension": 0,
					"m_Format": 0,
					"m_Offset": 0,
					"m_Stream": 0
				},
				{
					"m_Dimension": 0,
					"m_Format": 0,
					"m_Offset": 0,
					"m_Stream": 0
				},
				{
					"m_Dimension": 2,
					"m_Format": 0,
					"m_Offset": 0,
					"m_Stream": 1
				},
				{
					"m_Dimension": 0,
					"m_Format": 0,
					"m_Offset": 0,
					"m_Stream": 0
				},
				{
					"m_Dimension": 0,
					"m_Format": 0,
					"m_Offset": 0,
					"m_Stream": 0
				},
				{
					"m_Dimension": 0,
					"m_Format": 0,
					"m_Offset": 0,
					"m_Stream": 0
				},
				{
					"m_Dimension": 0,
					"m_Format": 0,
					"m_Offset": 0,
					"m_Stream": 0
				},
				{
					"m_Dimension": 0,
					"m_Format": 0,
					"m_Offset": 0,
					"m_Stream": 0
				},
				{
					"m_Dimension": 0,
					"m_Format": 0,
					"m_Offset": 0,
					"m_Stream": 0
				},
				{
					"m_Dimension": 0,
					"m_Format": 0,
					"m_Offset": 0,
					"m_Stream": 0
				},
				{
					"m_Dimension": 0,
					"m_Format": 0,
					"m_Offset": 0,
					"m_Stream": 0
				},
				{
					"m_Dimension": 0,
					"m_Format": 0,
					"m_Offset": 0,
					"m_Stream": 0
				}
			],
			"m_Data": "61H4Ps3MjL4AAAAAZmYGv83MjL4AAAAAZmYGv65HoT4AAAAA61H4Pq5HoT4AAAAAAAAAAAAAAAAAAAAAAAAAAAAAAAAAAAAAAAAAAAAAAAA=",
			"m_VertexCount": 4
		}
	},
	"m_Rect": {
		"m_Height": 59,
		"m_Width": 101,
		"m_X": 692,
		"m_Y": 576
	},
	"m_RenderDataKey": {
		"Key": {
			"m_Data_0_": 409282811,
			"m_Data_1_": 1122261259,
			"m_Data_2_": 2285992069,
			"m_Data_3_": 3206431891
		},
		"Value": 1789410473059956365
	},
	"m_SpriteAtlas": { "m_Collection": "cab-a1828797179c75fbf9033d39ad174438", "m_PathID": 0 },
	"m_SpriteID": ""
}